<?xml version="1.0" encoding="utf-8"?>
<Level>
  <LevelInfo>
    <BPM>90</BPM>
    <BeatPerBar>4</BeatPerBar>
    <BeatLen>16</BeatLen>
    <EnterTimeAdjust>370</EnterTimeAdjust>
    <NotePreShow>2</NotePreShow>
    <LevelTime>157333</LevelTime>
    <BarAmount>59</BarAmount>
    <BeginBarLen>4</BeginBarLen>
    <IsFourTrack>False</IsFourTrack>
    <TrackCount>5</TrackCount>
    <LevelPreTime>4000</LevelPreTime>
  </LevelInfo>
  <MusicInfo>
    <Title>金不奂</Title>
    <Artist>金志文/陈奂仁</Artist>
    <FilePath>audio/bgm/102015</FilePath>
  </MusicInfo>
  <SectionSeq>
    <Section type="previous" endbar="0" mark="" param1="wutai_scene_pre_script_1" />
    <Section type="begin" startbar="1" endbar="4" mark="" param1="wutai_scene_begin_script_1" />
    <Section type="note" startbar="5" endbar="26" mark="" param1="" />
    <Section type="showtime" startbar="27" endbar="30" mark="dance" param1="" />
    <Section type="note" startbar="33" endbar="55" mark="" param1="" />
    <Section type="showtime" startbar="56" endbar="59" mark="pose_xuanku" param1="" />
  </SectionSeq>
  <IndicatorResetPos PosNum="64">
    <Pos Bar="5" BeatPos="0" />
    <Pos Bar="7" BeatPos="0" />
    <Pos Bar="9" BeatPos="0" />
    <Pos Bar="13" BeatPos="0" />
    <Pos Bar="15" BeatPos="0" />
    <Pos Bar="17" BeatPos="0" />
    <Pos Bar="19" BeatPos="0" />
    <Pos Bar="20" BeatPos="40" />
    <Pos Bar="23" BeatPos="0" />
    <Pos Bar="25" BeatPos="0" />
    <Pos Bar="33" BeatPos="0" />
    <Pos Bar="34" BeatPos="56" />
    <Pos Bar="39" BeatPos="0" />
    <Pos Bar="42" BeatPos="56" />
    <Pos Bar="47" BeatPos="0" />
    <Pos Bar="49" BeatPos="0" />
    <Pos Bar="51" BeatPos="0" />
    <Pos Bar="53" BeatPos="0" />
  </IndicatorResetPos>
  <NoteInfo>
    <Normal PosNum="64">
      <Note Bar="5" BeatPos="0" Track="0" Type="0">
        <ScreenPos x="-429" y="-4">
          <FlyTrack name="波浪形" degree="135.3775" />
        </ScreenPos>
      </Note>
      <Note Bar="5" BeatPos="32" Track="0" Type="0">
        <ScreenPos x="250" y="100">
          <FlyTrack name="波浪形" degree="0" />
        </ScreenPos>
      </Note>
      <Note Bar="5" BeatPos="48" Track="0" Type="0">
        <ScreenPos x="250" y="-150">
          <FlyTrack name="波浪形" degree="0" />
        </ScreenPos>
      </Note>
      <Note Bar="6" BeatPos="0" Track="0" Type="0">
        <ScreenPos x="-350" y="-150">
          <FlyTrack name="波浪形" degree="64.19901" />
        </ScreenPos>
      </Note>
      <Note Bar="6" BeatPos="16" Track="0" Type="0">
        <ScreenPos x="150" y="150">
          <FlyTrack name="波浪形" degree="261.3692" />
        </ScreenPos>
      </Note>
      <Note Bar="6" BeatPos="24" Track="0" Type="0">
        <ScreenPos x="350" y="150">
          <FlyTrack name="波浪形" degree="269.9673" />
        </ScreenPos>
      </Note>
      <Note Bar="6" BeatPos="40" Track="0" Type="1" EndBar="6" EndPos="56" ID="1">
        <MoveTrack name="长按弧" degree="-180.8948" />
        <FlyTrack name="波浪形" degree="80.03215" />
        <ScreenPos x="600" y="-150" />
      </Note>
      <Note Bar="7" BeatPos="0" Track="0" Type="0">
        <ScreenPos x="-429" y="-4">
          <FlyTrack name="波浪形" degree="135.3775" />
        </ScreenPos>
      </Note>
      <Note Bar="7" BeatPos="32" Track="0" Type="0">
        <ScreenPos x="250" y="100">
          <FlyTrack name="波浪形" degree="0" />
        </ScreenPos>
      </Note>
      <Note Bar="7" BeatPos="48" Track="0" Type="0">
        <ScreenPos x="250" y="-150">
          <FlyTrack name="波浪形" degree="0" />
        </ScreenPos>
      </Note>
      <Note Bar="8" BeatPos="0" Track="0" Type="0">
        <ScreenPos x="-350" y="-150">
          <FlyTrack name="波浪形" degree="79.22432" />
        </ScreenPos>
      </Note>
      <Note Bar="8" BeatPos="16" Track="0" Type="0">
        <ScreenPos x="150" y="150">
          <FlyTrack name="波浪形" degree="261.3692" />
        </ScreenPos>
      </Note>
      <Note Bar="8" BeatPos="24" Track="0" Type="0">
        <ScreenPos x="350" y="150">
          <FlyTrack name="波浪形" degree="269.9673" />
        </ScreenPos>
      </Note>
      <Note Bar="8" BeatPos="40" Track="0" Type="1" EndBar="8" EndPos="56" ID="2">
        <MoveTrack name="长按弧" degree="-180.8948" />
        <FlyTrack name="波浪形" degree="80.03215" />
        <ScreenPos x="600" y="-150" />
      </Note>
      <Note Bar="9" BeatPos="0" Track="0" Type="0">
        <ScreenPos x="-300" y="-150">
          <FlyTrack name="波浪形" degree="78.30493" />
        </ScreenPos>
      </Note>
      <Note Bar="9" BeatPos="32" Track="0" Type="0">
        <ScreenPos x="200" y="100">
          <FlyTrack name="波浪形" degree="261.1054" />
        </ScreenPos>
      </Note>
      <Note Bar="9" BeatPos="48" Track="0" Type="0">
        <ScreenPos x="500" y="100">
          <FlyTrack name="波浪形" degree="268.9082" />
        </ScreenPos>
      </Note>
      <Note Bar="10" BeatPos="0" Track="0" Type="0">
        <ScreenPos x="-150" y="-150">
          <FlyTrack name="波浪形" degree="79.72098" />
        </ScreenPos>
      </Note>
      <Note Bar="10" BeatPos="16" Track="0" Type="0">
        <ScreenPos x="-400" y="150">
          <FlyTrack name="波浪形" degree="272.5299" />
        </ScreenPos>
      </Note>
      <Note Bar="10" BeatPos="24" Track="0" Type="0">
        <ScreenPos x="-600" y="150">
          <FlyTrack name="波浪形" degree="250.4389" />
        </ScreenPos>
      </Note>
      <Note Bar="10" BeatPos="40" Track="0" Type="0">
        <ScreenPos x="200" y="200">
          <FlyTrack name="波浪形" degree="-0.004776001" />
        </ScreenPos>
      </Note>
      <Note Bar="10" BeatPos="48" Track="0" Type="0">
        <ScreenPos x="200" y="0">
          <FlyTrack name="波浪形" degree="-2.01138" />
        </ScreenPos>
      </Note>
      <Note Bar="10" BeatPos="56" Track="0" Type="0">
        <ScreenPos x="200" y="-200">
          <FlyTrack name="波浪形" degree="1.554829" />
        </ScreenPos>
      </Note>
      <Note Bar="11" BeatPos="8" Track="0" Type="0">
        <ScreenPos x="-200" y="200">
          <FlyTrack name="波浪形" degree="174.8755" />
        </ScreenPos>
      </Note>
      <Note Bar="11" BeatPos="16" Track="0" Type="0">
        <ScreenPos x="-200" y="0">
          <FlyTrack name="波浪形" degree="173.6896" />
        </ScreenPos>
      </Note>
      <Note Bar="11" BeatPos="24" Track="0" Type="0">
        <ScreenPos x="-200" y="-200">
          <FlyTrack name="波浪形" degree="176.6494" />
        </ScreenPos>
      </Note>
      <Note Bar="11" BeatPos="40" Track="0" Type="0">
        <ScreenPos x="100" y="150">
          <FlyTrack name="波浪形" degree="249.9692" />
        </ScreenPos>
      </Note>
      <Note Bar="11" BeatPos="48" Track="0" Type="0">
        <ScreenPos x="300" y="50">
          <FlyTrack name="波浪形" degree="256.3629" />
        </ScreenPos>
      </Note>
      <Note Bar="11" BeatPos="56" Track="0" Type="0">
        <ScreenPos x="500" y="150">
          <FlyTrack name="波浪形" degree="273.8879" />
        </ScreenPos>
      </Note>
      <Note Bar="12" BeatPos="8" Track="0" Type="0">
        <ScreenPos x="-600" y="150">
          <FlyTrack name="波浪形" degree="-106.2275" />
        </ScreenPos>
      </Note>
      <Note Bar="12" BeatPos="16" Track="0" Type="0">
        <ScreenPos x="-400" y="50">
          <FlyTrack name="波浪形" degree="-97.96156" />
        </ScreenPos>
      </Note>
      <Note Bar="12" BeatPos="24" Track="0" Type="0">
        <ScreenPos x="-200" y="150">
          <FlyTrack name="波浪形" degree="-83.23679" />
        </ScreenPos>
      </Note>
      <Note Bar="12" BeatPos="40" Track="0" Type="1" EndBar="12" EndPos="56" ID="3">
        <MoveTrack name="长按直线2" degree="0" />
        <FlyTrack name="波浪形" degree="269.3887" />
        <ScreenPos x="350" y="150" />
      </Note>
      <Note Bar="13" BeatPos="0" Track="0" Type="0">
        <ScreenPos x="-350" y="-150">
          <FlyTrack name="波浪形" degree="81.42523" />
        </ScreenPos>
      </Note>
      <Note Bar="13" BeatPos="16" Track="0" Type="0">
        <ScreenPos x="350" y="-150">
          <FlyTrack name="波浪形" degree="-4.123138" />
        </ScreenPos>
      </Note>
      <Note Bar="13" BeatPos="32" Track="0" Type="0">
        <ScreenPos x="350" y="150">
          <FlyTrack name="波浪形" degree="244.475" />
        </ScreenPos>
      </Note>
      <Note Bar="13" BeatPos="48" Track="0" Type="0">
        <ScreenPos x="-350" y="150">
          <FlyTrack name="波浪形" degree="173.599" />
        </ScreenPos>
      </Note>
      <Note Bar="14" BeatPos="0" Track="0" Type="0">
        <ScreenPos x="-350" y="-150">
          <FlyTrack name="波浪形" degree="60.84132" />
        </ScreenPos>
      </Note>
      <Note Bar="14" BeatPos="16" Track="0" Type="0">
        <ScreenPos x="0" y="-150">
          <FlyTrack name="波浪形" degree="10.64806" />
        </ScreenPos>
      </Note>
      <Note Bar="14" BeatPos="32" Track="0" Type="0">
        <ScreenPos x="350" y="-150">
          <FlyTrack name="波浪形" degree="10.57085" />
        </ScreenPos>
      </Note>
      <Note Bar="14" BeatPos="48" Track="0" Type="0">
        <ScreenPos x="600" y="0">
          <FlyTrack name="波浪形" degree="299.0378" />
        </ScreenPos>
      </Note>
      <Note Bar="15" BeatPos="0" Track="0" Type="0">
        <ScreenPos x="350" y="200">
          <FlyTrack name="波浪形" degree="194.5649" />
        </ScreenPos>
      </Note>
      <Note Bar="15" BeatPos="16" Track="0" Type="0">
        <ScreenPos x="0" y="0">
          <FlyTrack name="波浪形" degree="133.3076" />
        </ScreenPos>
      </Note>
      <Note Bar="15" BeatPos="32" Track="0" Type="0">
        <ScreenPos x="-300" y="200">
          <FlyTrack name="波浪形" degree="220.281" />
        </ScreenPos>
      </Note>
      <Note Bar="15" BeatPos="48" Track="0" Type="0">
        <ScreenPos x="-600" y="0">
          <FlyTrack name="波浪形" degree="123.5985" />
        </ScreenPos>
      </Note>
      <Note Bar="16" BeatPos="0" Track="0" Type="0">
        <ScreenPos x="-300" y="-200">
          <FlyTrack name="波浪形" degree="10.21645" />
        </ScreenPos>
      </Note>
      <Note Bar="16" BeatPos="16" Track="0" Type="0">
        <ScreenPos x="200" y="-200">
          <FlyTrack name="波浪形" degree="3.381226" />
        </ScreenPos>
      </Note>
      <Note Bar="16" BeatPos="24" Track="0" Type="0">
        <ScreenPos x="200" y="0">
          <FlyTrack name="波浪形" degree="0" />
        </ScreenPos>
      </Note>
      <Note Bar="16" BeatPos="40" Track="0" Type="1" EndBar="16" EndPos="56" ID="4">
        <MoveTrack name="长按弧" degree="-180" />
        <FlyTrack name="波浪形" degree="261.1048" />
        <ScreenPos x="500" y="150" />
      </Note>
      <Note Bar="17" BeatPos="0" Track="0" Type="0">
        <ScreenPos x="-350" y="200">
          <FlyTrack name="波浪形" degree="-99.27264" />
        </ScreenPos>
      </Note>
      <Note Bar="17" BeatPos="16" Track="0" Type="0">
        <ScreenPos x="0" y="0">
          <FlyTrack name="波浪形" degree="38.79531" />
        </ScreenPos>
      </Note>
      <Note Bar="17" BeatPos="32" Track="0" Type="0">
        <ScreenPos x="300" y="200">
          <FlyTrack name="波浪形" degree="-40.28098" />
        </ScreenPos>
      </Note>
      <Note Bar="17" BeatPos="48" Track="0" Type="0">
        <ScreenPos x="600" y="0">
          <FlyTrack name="波浪形" degree="42.3643" />
        </ScreenPos>
      </Note>
      <Note Bar="18" BeatPos="0" Track="0" Type="0">
        <ScreenPos x="300" y="-200">
          <FlyTrack name="波浪形" degree="156.9375" />
        </ScreenPos>
      </Note>
      <Note Bar="18" BeatPos="16" Track="0" Type="0">
        <ScreenPos x="-200" y="-200">
          <FlyTrack name="波浪形" degree="176.6188" />
        </ScreenPos>
      </Note>
      <Note Bar="18" BeatPos="24" Track="0" Type="0">
        <ScreenPos x="-200" y="0">
          <FlyTrack name="波浪形" degree="180" />
        </ScreenPos>
      </Note>
      <Note Bar="18" BeatPos="40" Track="0" Type="1" EndBar="18" EndPos="56" ID="5">
        <MoveTrack name="长按弧" degree="360" />
        <FlyTrack name="波浪形" degree="-97.6068" />
        <ScreenPos x="-500" y="150" />
      </Note>
      <Note Bar="19" BeatPos="0" Track="0" Type="0">
        <ScreenPos x="-200" y="-150">
          <FlyTrack name="波浪形" degree="76.0403" />
        </ScreenPos>
      </Note>
      <Note Bar="19" BeatPos="16" Track="0" Type="0">
        <ScreenPos x="200" y="-150">
          <FlyTrack name="波浪形" degree="353.3062" />
        </ScreenPos>
      </Note>
      <Note Bar="19" BeatPos="32" Track="0" Type="0">
        <ScreenPos x="200" y="150">
          <FlyTrack name="波浪形" degree="-116.6353" />
        </ScreenPos>
      </Note>
      <Note Bar="19" BeatPos="48" Track="0" Type="0">
        <ScreenPos x="-200" y="150">
          <FlyTrack name="波浪形" degree="163.8564" />
        </ScreenPos>
      </Note>
      <Note Bar="20" BeatPos="0" Track="0" Type="0">
        <ScreenPos x="-200" y="-150">
          <FlyTrack name="波浪形" degree="64.30193" />
        </ScreenPos>
      </Note>
      <Note Bar="20" BeatPos="16" Track="0" Type="0">
        <ScreenPos x="-420" y="150">
          <FlyTrack name="波浪形" degree="257.7687" />
        </ScreenPos>
      </Note>
      <Note Bar="20" BeatPos="24" Track="0" Type="0">
        <ScreenPos x="-600" y="150">
          <FlyTrack name="波浪形" degree="253.716" />
        </ScreenPos>
      </Note>
      <Note Bar="20" BeatPos="40" Track="0" Type="0">
        <ScreenPos x="-50" y="150">
          <FlyTrack name="波浪形" degree="248.3555" />
        </ScreenPos>
      </Note>
      <Note Bar="20" BeatPos="48" Track="0" Type="0">
        <ScreenPos x="150" y="150">
          <FlyTrack name="波浪形" degree="259.8803" />
        </ScreenPos>
      </Note>
      <Note Bar="20" BeatPos="56" Track="0" Type="0">
        <ScreenPos x="350" y="150">
          <FlyTrack name="波浪形" degree="274.5247" />
        </ScreenPos>
      </Note>
      <Note Bar="21" BeatPos="8" Track="0" Type="0">
        <ScreenPos x="50" y="-150">
          <FlyTrack name="波浪形" degree="70.98376" />
        </ScreenPos>
      </Note>
      <Note Bar="21" BeatPos="16" Track="0" Type="0">
        <ScreenPos x="-150" y="-150">
          <FlyTrack name="波浪形" degree="72.01752" />
        </ScreenPos>
      </Note>
      <Note Bar="21" BeatPos="24" Track="0" Type="0">
        <ScreenPos x="-350" y="-150">
          <FlyTrack name="波浪形" degree="74.1306" />
        </ScreenPos>
      </Note>
      <Note Bar="21" BeatPos="48" Track="0" Type="0">
        <ScreenPos x="-550" y="150">
          <FlyTrack name="波浪形" degree="260.2293" />
        </ScreenPos>
      </Note>
      <Note Bar="22" BeatPos="0" Track="0" Type="1" EndBar="22" EndPos="16" ID="6">
        <MoveTrack name="长按直线2" degree="0" />
        <FlyTrack name="波浪形" degree="77.94733" />
        <ScreenPos x="300" y="-150" />
      </Note>
      <Note Bar="22" BeatPos="24" Track="0" Type="0">
        <ScreenPos x="-100" y="100">
          <FlyTrack name="波浪形" degree="259.1609" />
        </ScreenPos>
      </Note>
      <Note Bar="22" BeatPos="40" Track="0" Type="0">
        <ScreenPos x="-350" y="100">
          <FlyTrack name="波浪形" degree="262.3669" />
        </ScreenPos>
      </Note>
      <Note Bar="23" BeatPos="0" Track="0" Type="0">
        <ScreenPos x="250" y="-150">
          <FlyTrack name="波浪形" degree="80.46865" />
        </ScreenPos>
      </Note>
      <Note Bar="23" BeatPos="32" Track="0" Type="0">
        <ScreenPos x="-150" y="150">
          <FlyTrack name="波浪形" degree="261.8284" />
        </ScreenPos>
      </Note>
      <Note Bar="23" BeatPos="48" Track="0" Type="0">
        <ScreenPos x="-450" y="150">
          <FlyTrack name="波浪形" degree="260.4527" />
        </ScreenPos>
      </Note>
      <Note Bar="24" BeatPos="0" Track="0" Type="0">
        <ScreenPos x="-150" y="-150">
          <FlyTrack name="波浪形" degree="77.92921" />
        </ScreenPos>
      </Note>
      <Note Bar="24" BeatPos="16" Track="0" Type="0">
        <ScreenPos x="300" y="150">
          <FlyTrack name="波浪形" degree="0" />
        </ScreenPos>
      </Note>
      <Note Bar="24" BeatPos="24" Track="0" Type="0">
        <ScreenPos x="300" y="-50">
          <FlyTrack name="波浪形" degree="0" />
        </ScreenPos>
      </Note>
      <Note Bar="24" BeatPos="48" Track="0" Type="0">
        <ScreenPos x="-250" y="-150">
          <FlyTrack name="波浪形" degree="74.92062" />
        </ScreenPos>
      </Note>
      <Note Bar="25" BeatPos="0" Track="0" Type="0">
        <ScreenPos x="-550" y="150">
          <FlyTrack name="波浪形" degree="261.91" />
        </ScreenPos>
      </Note>
      <Note Bar="25" BeatPos="32" Track="0" Type="0">
        <ScreenPos x="100" y="150">
          <FlyTrack name="波浪形" degree="261.051" />
        </ScreenPos>
      </Note>
      <Note Bar="25" BeatPos="48" Track="0" Type="0">
        <ScreenPos x="400" y="150">
          <FlyTrack name="波浪形" degree="262.347" />
        </ScreenPos>
      </Note>
      <Note Bar="26" BeatPos="0" Track="0" Type="0">
        <ScreenPos x="200" y="-200">
          <FlyTrack name="波浪形" degree="79.53978" />
        </ScreenPos>
      </Note>
      <Note Bar="26" BeatPos="16" Track="0" Type="0">
        <ScreenPos x="-200" y="-100">
          <FlyTrack name="波浪形" degree="167.7453" />
        </ScreenPos>
      </Note>
      <Note Bar="26" BeatPos="24" Track="0" Type="0">
        <ScreenPos x="-200" y="130">
          <FlyTrack name="波浪形" degree="169.8791" />
        </ScreenPos>
      </Note>
      <Note Bar="26" BeatPos="48" Track="0" Type="0">
        <ScreenPos x="500" y="150">
          <FlyTrack name="波浪形" degree="261.8529" />
        </ScreenPos>
      </Note>
      <Note Bar="27" BeatPos="0" Track="0" Type="0">
        <ScreenPos x="250" y="-150">
          <FlyTrack name="波浪形" degree="78.63663" />
        </ScreenPos>
      </Note>
      <Note Bar="33" BeatPos="0" Track="3" Type="0">
        <ScreenPos x="-250" y="-150">
          <FlyTrack name="波浪形" degree="74.40374" />
        </ScreenPos>
      </Note>
      <Note Bar="33" BeatPos="32" Track="3" Type="0">
        <ScreenPos x="150" y="150">
          <FlyTrack name="波浪形" degree="-102.3722" />
        </ScreenPos>
      </Note>
      <Note Bar="33" BeatPos="48" Track="3" Type="0">
        <ScreenPos x="450" y="150">
          <FlyTrack name="波浪形" degree="-89.05984" />
        </ScreenPos>
      </Note>
      <Note Bar="34" BeatPos="0" Track="3" Type="0">
        <ScreenPos x="-100" y="-150">
          <FlyTrack name="波浪形" degree="80.46199" />
        </ScreenPos>
      </Note>
      <Note Bar="34" BeatPos="16" Track="3" Type="0">
        <ScreenPos x="-500" y="150">
          <FlyTrack name="波浪形" degree="180" />
        </ScreenPos>
      </Note>
      <Note Bar="34" BeatPos="24" Track="3" Type="0">
        <ScreenPos x="-500" y="-50">
          <FlyTrack name="波浪形" degree="165.6921" />
        </ScreenPos>
      </Note>
      <Note Bar="34" BeatPos="40" Track="3" Type="0">
        <ScreenPos x="250" y="-150">
          <FlyTrack name="波浪形" degree="79.58337" />
        </ScreenPos>
      </Note>
      <Note Bar="34" BeatPos="56" Track="3" Type="0">
        <ScreenPos x="500" y="150">
          <FlyTrack name="波浪形" degree="-97.86787" />
        </ScreenPos>
      </Note>
      <Note Bar="35" BeatPos="16" Track="3" Type="1" EndBar="35" EndPos="32" ID="7">
        <MoveTrack name="长按直线2" degree="0" />
        <FlyTrack name="波浪形" degree="254.2974" />
        <ScreenPos x="-250" y="150" />
      </Note>
      <Note Bar="35" BeatPos="40" Track="3" Type="0">
        <ScreenPos x="-450" y="-150">
          <FlyTrack name="波浪形" degree="-284.2431" />
        </ScreenPos>
      </Note>
      <Note Bar="35" BeatPos="56" Track="3" Type="0">
        <ScreenPos x="-150" y="-150">
          <FlyTrack name="波浪形" degree="-282.3763" />
        </ScreenPos>
      </Note>
      <Note Bar="36" BeatPos="16" Track="3" Type="1" EndBar="36" EndPos="32" ID="8">
        <MoveTrack name="长按直线2" degree="0" />
        <FlyTrack name="波浪形" degree="259.6761" />
        <ScreenPos x="250" y="150" />
      </Note>
      <Note Bar="36" BeatPos="40" Track="3" Type="0">
        <ScreenPos x="550" y="-150">
          <FlyTrack name="波浪形" degree="78.91756" />
        </ScreenPos>
      </Note>
      <Note Bar="36" BeatPos="56" Track="3" Type="0">
        <ScreenPos x="250" y="-150">
          <FlyTrack name="波浪形" degree="75.45012" />
        </ScreenPos>
      </Note>
      <Note Bar="37" BeatPos="16" Track="3" Type="0">
        <ScreenPos x="-100" y="-150">
          <FlyTrack name="波浪形" degree="71.71614" />
        </ScreenPos>
      </Note>
      <Note Bar="37" BeatPos="32" Track="3" Type="1" EndBar="37" EndPos="48" ID="9">
        <MoveTrack name="长按直线2" degree="118.0902" />
        <FlyTrack name="波浪形" degree="247.6954" />
        <ScreenPos x="-550" y="150" />
      </Note>
      <Note Bar="37" BeatPos="56" Track="3" Type="1" EndBar="38" EndPos="40" ID="10">
        <MoveTrack name="长按波浪" degree="180" />
        <FlyTrack name="波浪形" degree="264.3367" />
        <ScreenPos x="550" y="150" />
      </Note>
      <Note Bar="39" BeatPos="0" Track="0" Type="1" EndBar="39" EndPos="32" ID="11">
        <MoveTrack name="长按2拍直角" degree="-41.85531" />
        <FlyTrack name="波浪形" degree="77.63155" />
        <ScreenPos x="-400" y="-150" />
      </Note>
      <Note Bar="40" BeatPos="0" Track="0" Type="0">
        <ScreenPos x="150" y="-150">
          <FlyTrack name="波浪形" degree="76.00363" />
        </ScreenPos>
      </Note>
      <Note Bar="40" BeatPos="18" Track="0" Type="0">
        <ScreenPos x="400" y="150">
          <FlyTrack name="波浪形" degree="254.5371" />
        </ScreenPos>
      </Note>
      <Note Bar="40" BeatPos="26" Track="0" Type="0">
        <ScreenPos x="600" y="150">
          <FlyTrack name="波浪形" degree="273.791" />
        </ScreenPos>
      </Note>
      <Note Bar="41" BeatPos="0" Track="0" Type="0">
        <ScreenPos x="-350" y="150">
          <FlyTrack name="波浪形" degree="203.7842" />
        </ScreenPos>
      </Note>
      <Note Bar="41" BeatPos="34" Track="0" Type="0">
        <ScreenPos x="350" y="-150">
          <FlyTrack name="波浪形" degree="45.45421" />
        </ScreenPos>
      </Note>
      <Note Bar="41" BeatPos="50" Track="0" Type="0">
        <ScreenPos x="-350" y="-150">
          <FlyTrack name="波浪形" degree="134.5458" />
        </ScreenPos>
      </Note>
      <Note Bar="42" BeatPos="2" Track="0" Type="0">
        <ScreenPos x="350" y="150">
          <FlyTrack name="波浪形" degree="302.3293" />
        </ScreenPos>
      </Note>
      <Note Bar="42" BeatPos="18" Track="0" Type="0">
        <ScreenPos x="-200" y="150">
          <FlyTrack name="波浪形" degree="229.0673" />
        </ScreenPos>
      </Note>
      <Note Bar="42" BeatPos="26" Track="0" Type="0">
        <ScreenPos x="-400" y="150">
          <FlyTrack name="波浪形" degree="232.4755" />
        </ScreenPos>
      </Note>
      <Note Bar="42" BeatPos="56" Track="0" Type="0">
        <ScreenPos x="400" y="-150">
          <FlyTrack name="波浪形" degree="80.53893" />
        </ScreenPos>
      </Note>
      <Note Bar="43" BeatPos="8" Track="0" Type="0">
        <ScreenPos x="100" y="50">
          <FlyTrack name="波浪形" degree="195.3959" />
        </ScreenPos>
      </Note>
      <Note Bar="43" BeatPos="24" Track="0" Type="0">
        <ScreenPos x="-200" y="-150">
          <FlyTrack name="波浪形" degree="125.5025" />
        </ScreenPos>
      </Note>
      <Note Bar="43" BeatPos="40" Track="0" Type="1" EndBar="43" EndPos="56" ID="12">
        <MoveTrack name="长按弧" degree="0" />
        <FlyTrack name="波浪形" degree="225.9294" />
        <ScreenPos x="-500" y="50" />
      </Note>
      <Note Bar="44" BeatPos="8" Track="0" Type="0">
        <ScreenPos x="150" y="100">
          <FlyTrack name="波浪形" degree="258.4667" />
        </ScreenPos>
      </Note>
      <Note Bar="44" BeatPos="26" Track="0" Type="1" EndBar="44" EndPos="42" ID="13">
        <MoveTrack name="长按直线2" degree="0" />
        <FlyTrack name="波浪形" degree="255.4214" />
        <ScreenPos x="400" y="100" />
      </Note>
      <Note Bar="44" BeatPos="48" Track="0" Type="0">
        <ScreenPos x="-100" y="-150">
          <FlyTrack name="波浪形" degree="70.00516" />
        </ScreenPos>
      </Note>
      <Note Bar="44" BeatPos="56" Track="0" Type="1" EndBar="46" EndPos="56" ID="14">
        <MoveTrack name="长按三叶草" degree="-31.45815" />
        <FlyTrack name="波浪形" degree="94.22729" />
        <ScreenPos x="-300" y="-150" />
      </Note>
      <Note Bar="47" BeatPos="0" Track="3" Type="0">
        <ScreenPos x="200" y="200">
          <FlyTrack name="波浪形" degree="305.5016" />
        </ScreenPos>
      </Note>
      <Note Bar="47" BeatPos="16" Track="3" Type="0">
        <ScreenPos x="-200" y="200">
          <FlyTrack name="波浪形" degree="-144.8912" />
        </ScreenPos>
      </Note>
      <Note Bar="47" BeatPos="32" Track="3" Type="0">
        <ScreenPos x="200" y="-200">
          <FlyTrack name="波浪形" degree="38.15387" />
        </ScreenPos>
      </Note>
      <Note Bar="47" BeatPos="48" Track="3" Type="0">
        <ScreenPos x="-200" y="-200">
          <FlyTrack name="波浪形" degree="121.4813" />
        </ScreenPos>
      </Note>
      <Note Bar="48" BeatPos="0" Track="3" Type="0">
        <ScreenPos x="-600" y="-200">
          <FlyTrack name="波浪形" degree="173.8072" />
        </ScreenPos>
      </Note>
      <Note Bar="48" BeatPos="16" Track="3" Type="0">
        <ScreenPos x="-600" y="200">
          <FlyTrack name="波浪形" degree="-97.95508" />
        </ScreenPos>
      </Note>
      <Note Bar="48" BeatPos="24" Track="3" Type="0">
        <ScreenPos x="-400" y="200">
          <FlyTrack name="波浪形" degree="-67.58427" />
        </ScreenPos>
      </Note>
      <Note Bar="48" BeatPos="48" Track="3" Type="0">
        <ScreenPos x="0" y="200">
          <FlyTrack name="波浪形" degree="-0.5584106" />
        </ScreenPos>
      </Note>
      <Note Bar="49" BeatPos="0" Track="3" Type="0">
        <ScreenPos x="600" y="200">
          <FlyTrack name="波浪形" degree="-7.269409" />
        </ScreenPos>
      </Note>
      <Note Bar="49" BeatPos="16" Track="3" Type="0">
        <ScreenPos x="600" y="-200">
          <FlyTrack name="波浪形" degree="86.04054" />
        </ScreenPos>
      </Note>
      <Note Bar="49" BeatPos="32" Track="3" Type="0">
        <ScreenPos x="200" y="-200">
          <FlyTrack name="波浪形" degree="174.1395" />
        </ScreenPos>
      </Note>
      <Note Bar="49" BeatPos="48" Track="3" Type="0">
        <ScreenPos x="200" y="200">
          <FlyTrack name="波浪形" degree="-98.73074" />
        </ScreenPos>
      </Note>
      <Note Bar="50" BeatPos="0" Track="3" Type="0">
        <ScreenPos x="600" y="200">
          <FlyTrack name="波浪形" degree="-4.236847" />
        </ScreenPos>
      </Note>
      <Note Bar="50" BeatPos="16" Track="3" Type="0">
        <ScreenPos x="-100" y="-150">
          <FlyTrack name="波浪形" degree="166.0661" />
        </ScreenPos>
      </Note>
      <Note Bar="50" BeatPos="24" Track="3" Type="0">
        <ScreenPos x="-100" y="50">
          <FlyTrack name="波浪形" degree="-189.8295" />
        </ScreenPos>
      </Note>
      <Note Bar="50" BeatPos="40" Track="3" Type="0">
        <ScreenPos x="350" y="100">
          <FlyTrack name="波浪形" degree="-99.53574" />
        </ScreenPos>
      </Note>
      <Note Bar="51" BeatPos="0" Track="0" Type="0">
        <ScreenPos x="-250" y="-150">
          <FlyTrack name="波浪形" degree="77.13242" />
        </ScreenPos>
      </Note>
      <Note Bar="51" BeatPos="16" Track="0" Type="0">
        <ScreenPos x="150" y="150">
          <FlyTrack name="波浪形" degree="-97.41904" />
        </ScreenPos>
      </Note>
      <Note Bar="51" BeatPos="32" Track="0" Type="0">
        <ScreenPos x="350" y="-150">
          <FlyTrack name="波浪形" degree="-281.1463" />
        </ScreenPos>
      </Note>
      <Note Bar="51" BeatPos="40" Track="0" Type="0">
        <ScreenPos x="550" y="-150">
          <FlyTrack name="波浪形" degree="75.16544" />
        </ScreenPos>
      </Note>
      <Note Bar="52" BeatPos="0" Track="0" Type="0">
        <ScreenPos x="-250" y="-150">
          <FlyTrack name="波浪形" degree="77.13242" />
        </ScreenPos>
      </Note>
      <Note Bar="52" BeatPos="16" Track="0" Type="0">
        <ScreenPos x="150" y="150">
          <FlyTrack name="波浪形" degree="-97.41904" />
        </ScreenPos>
      </Note>
      <Note Bar="52" BeatPos="32" Track="0" Type="0">
        <ScreenPos x="350" y="-150">
          <FlyTrack name="波浪形" degree="-281.1463" />
        </ScreenPos>
      </Note>
      <Note Bar="52" BeatPos="40" Track="0" Type="0">
        <ScreenPos x="550" y="-150">
          <FlyTrack name="波浪形" degree="75.16544" />
        </ScreenPos>
      </Note>
      <Note Bar="53" BeatPos="0" Track="3" Type="0">
        <ScreenPos x="-350" y="150">
          <FlyTrack name="波浪形" degree="-101.7434" />
        </ScreenPos>
      </Note>
      <Note Bar="53" BeatPos="16" Track="3" Type="0">
        <ScreenPos x="150" y="150">
          <FlyTrack name="波浪形" degree="0.8466339" />
        </ScreenPos>
      </Note>
      <Note Bar="53" BeatPos="32" Track="3" Type="0">
        <ScreenPos x="150" y="-150">
          <FlyTrack name="波浪形" degree="99.90106" />
        </ScreenPos>
      </Note>
      <Note Bar="53" BeatPos="48" Track="3" Type="0">
        <ScreenPos x="-350" y="-150">
          <FlyTrack name="波浪形" degree="-183.9457" />
        </ScreenPos>
      </Note>
      <Note Bar="54" BeatPos="0" Track="3" Type="0">
        <ScreenPos x="-350" y="150">
          <FlyTrack name="波浪形" degree="281.5421" />
        </ScreenPos>
      </Note>
      <Note Bar="54" BeatPos="16" Track="3" Type="0">
        <ScreenPos x="150" y="150">
          <FlyTrack name="波浪形" degree="-4.107506" />
        </ScreenPos>
      </Note>
      <Note Bar="54" BeatPos="32" Track="3" Type="0">
        <ScreenPos x="150" y="-150">
          <FlyTrack name="波浪形" degree="102.8261" />
        </ScreenPos>
      </Note>
      <Note Bar="54" BeatPos="48" Track="3" Type="0">
        <ScreenPos x="-100" y="50">
          <FlyTrack name="波浪形" degree="-142.766" />
        </ScreenPos>
      </Note>
      <Note Bar="55" BeatPos="0" Track="3" Type="0">
        <ScreenPos x="-350" y="-150">
          <FlyTrack name="波浪形" degree="117.976" />
        </ScreenPos>
      </Note>
      <Note Bar="55" BeatPos="16" Track="3" Type="0">
        <ScreenPos x="-600" y="100">
          <FlyTrack name="波浪形" degree="236.9384" />
        </ScreenPos>
      </Note>
      <Note Bar="55" BeatPos="32" Track="3" Type="0">
        <ScreenPos x="-150" y="100">
          <FlyTrack name="波浪形" degree="0" />
        </ScreenPos>
      </Note>
      <Note Bar="55" BeatPos="48" Track="3" Type="0">
        <ScreenPos x="300" y="100">
          <FlyTrack name="波浪形" degree="7.592422" />
        </ScreenPos>
      </Note>
    </Normal>
  </NoteInfo>
  <ActionSeq type="1">
    <ActionList start_bar="5" dance_len="1" seq_len="4" level="2" type="" />
    <ActionList start_bar="9" dance_len="2" seq_len="4" level="2" type="" />
    <ActionList start_bar="13" dance_len="2" seq_len="2" level="2" type="" />
    <ActionList start_bar="15" dance_len="2" seq_len="4" level="2" type="" />
    <ActionList start_bar="19" dance_len="2" seq_len="4" level="2" type="" />
    <ActionList start_bar="23" dance_len="2" seq_len="4" level="2" type="" />
    <ActionList start_bar="27" dance_len="4" seq_len="4" level="2" type="" />
    <ActionList start_bar="31" dance_len="1" seq_len="4" level="2" type="" />
    <ActionList start_bar="35" dance_len="2" seq_len="4" level="2" type="" />
    <ActionList start_bar="39" dance_len="2" seq_len="4" level="2" type="" />
    <ActionList start_bar="43" dance_len="2" seq_len="4" level="2" type="" />
    <ActionList start_bar="47" dance_len="2" seq_len="8" level="2" type="" />
    <ActionList start_bar="55" dance_len="1" seq_len="1" level="2" type="" />
    <ActionList start_bar="56" dance_len="4" seq_len="4" level="2" type="" />
  </ActionSeq>
  <CameraSeq>
    <Camera name="SL" bar="5" pos="0" end_bar="7" end_pos="0" />
    <Camera name="NL" bar="7" pos="0" end_bar="9" end_pos="0" />
    <Camera name="YAOBI_FN_03" bar="9" pos="0" end_bar="13" end_pos="0" />
    <Camera name="BL_U" bar="13" pos="0" end_bar="15" end_pos="0" />
    <Camera name="SC" bar="15" pos="0" end_bar="17" end_pos="0" />
    <Camera name="NC" bar="17" pos="0" end_bar="19" end_pos="0" />
    <Camera name="YAOBI_LR_04" bar="19" pos="0" end_bar="23" end_pos="0" />
    <Camera name="YAOBI_RL_06" bar="23" pos="0" end_bar="27" end_pos="0" />
    <Camera name="FC" bar="27" pos="0" end_bar="31" end_pos="0" />
    <Camera name="YAOBI_LR_08" bar="31" pos="0" end_bar="35" end_pos="0" />
    <Camera name="YAOBI_RL_07" bar="35" pos="0" end_bar="39" end_pos="0" />
    <Camera name="SL" bar="39" pos="0" end_bar="41" end_pos="0" />
    <Camera name="NR" bar="41" pos="0" end_bar="43" end_pos="0" />
    <Camera name="YAOBI_LR_13" bar="43" pos="0" end_bar="47" end_pos="0" />
    <Camera name="YAOBI_RL_04" bar="47" pos="0" end_bar="51" end_pos="0" />
    <Camera name="YAOBI_LR_06" bar="51" pos="0" end_bar="55" end_pos="0" />
    <Camera name="NC" bar="55" pos="0" end_bar="56" end_pos="0" />
    <Camera name="FC" bar="56" pos="0" end_bar="60" end_pos="0" />
  </CameraSeq>
  <DancerSort>
    <Bar>11</Bar>
    <Bar>13</Bar>
    <Bar>15</Bar>
    <Bar>17</Bar>
    <Bar>19</Bar>
    <Bar>21</Bar>
    <Bar>23</Bar>
    <Bar>25</Bar>
    <Bar>33</Bar>
    <Bar>34</Bar>
    <Bar>35</Bar>
    <Bar>37</Bar>
    <Bar>39</Bar>
    <Bar>41</Bar>
    <Bar>43</Bar>
    <Bar>45</Bar>
    <Bar>47</Bar>
    <Bar>49</Bar>
    <Bar>51</Bar>
    <Bar>53</Bar>
    <Bar>55</Bar>
  </DancerSort>
  <StageEffectSeq>
    <effect name="wutai_scene_global_script" bar="-1" length="-1" />
    <effect name="wutai_scene_note_biaozhun_01" bar="5" length="22" />
    <effect name="wutai_scene_note_biaozhun_01" bar="31" length="25" />
    <effect name="wutai_scene_note_biaozhun_01" bar="60" length="-1" />
  </StageEffectSeq>
</Level>