<?xml version="1.0" encoding="utf-8"?>
<Level>
  <LevelInfo>
    <BPM>132</BPM>
    <BeatPerBar>4</BeatPerBar>
    <BeatLen>16</BeatLen>
    <EnterTimeAdjust>1913</EnterTimeAdjust>
    <NotePreShow>2</NotePreShow>
    <LevelTime>160000</LevelTime>
    <BarAmount>88</BarAmount>
    <BeginBarLen>8</BeginBarLen>
    <IsFourTrack>False</IsFourTrack>
    <TrackCount>5</TrackCount>
    <LevelPreTime>4000</LevelPreTime>
  </LevelInfo>
  <MusicInfo>
    <Title>なのです!</Title>
    <Artist>北のロリ</Artist>
    <FilePath>audio/bgm/102821</FilePath>
  </MusicInfo>
  <SectionSeq>
    <Section type="previous" endbar="0" mark="" param1="wutai_scene_pre_script_2" />
    <Section type="begin" startbar="1" endbar="8" mark="" param1="wutai_scene_begin_script_2" />
    <Section type="note" startbar="9" endbar="44" mark="" param1="" />
    <Section type="showtime" startbar="45" endbar="48" mark="dance" param1="" />
    <Section type="note" startbar="51" endbar="84" mark="" param1="" />
    <Section type="showtime" startbar="85" endbar="88" mark="pose_yangguang" param1="" />
  </SectionSeq>
  <IndicatorResetPos PosNum="64">
    <Pos Bar="9" BeatPos="16" />
    <Pos Bar="11" BeatPos="16" />
    <Pos Bar="13" BeatPos="16" />
    <Pos Bar="15" BeatPos="16" />
    <Pos Bar="17" BeatPos="16" />
    <Pos Bar="19" BeatPos="16" />
    <Pos Bar="21" BeatPos="16" />
    <Pos Bar="23" BeatPos="16" />
    <Pos Bar="24" BeatPos="40" />
    <Pos Bar="26" BeatPos="40" />
    <Pos Bar="28" BeatPos="40" />
    <Pos Bar="30" BeatPos="40" />
    <Pos Bar="33" BeatPos="0" />
    <Pos Bar="34" BeatPos="0" />
    <Pos Bar="35" BeatPos="0" />
    <Pos Bar="37" BeatPos="0" />
    <Pos Bar="38" BeatPos="0" />
    <Pos Bar="39" BeatPos="0" />
    <Pos Bar="40" BeatPos="48" />
    <Pos Bar="51" BeatPos="0" />
    <Pos Bar="52" BeatPos="48" />
    <Pos Bar="54" BeatPos="48" />
    <Pos Bar="56" BeatPos="48" />
    <Pos Bar="58" BeatPos="48" />
    <Pos Bar="61" BeatPos="0" />
    <Pos Bar="63" BeatPos="0" />
    <Pos Bar="65" BeatPos="0" />
    <Pos Bar="67" BeatPos="0" />
    <Pos Bar="69" BeatPos="0" />
    <Pos Bar="70" BeatPos="0" />
    <Pos Bar="71" BeatPos="0" />
    <Pos Bar="73" BeatPos="0" />
    <Pos Bar="74" BeatPos="0" />
    <Pos Bar="75" BeatPos="0" />
    <Pos Bar="76" BeatPos="48" />
    <Pos Bar="81" BeatPos="0" />
    <Pos Bar="83" BeatPos="0" />
  </IndicatorResetPos>
  <NoteInfo>
    <Normal PosNum="64">
      <Note Bar="9" BeatPos="16" Track="0" Type="2" EndBar="9" EndPos="48" ID="1">
        <MoveTrack name="滑动问号" degree="33.79725" />
        <FlyTrack name="波浪形" degree="354.9144" />
        <ScreenPos x="325" y="75" />
      </Note>
      <Note Bar="10" BeatPos="0" Track="0" Type="0">
        <ScreenPos x="-600" y="200">
          <FlyTrack name="波浪形" degree="264.5949" />
        </ScreenPos>
      </Note>
      <Note Bar="10" BeatPos="16" Track="0" Type="0">
        <ScreenPos x="-200" y="-50">
          <FlyTrack name="波浪形" degree="31.79587" />
        </ScreenPos>
      </Note>
      <Note Bar="10" BeatPos="32" Track="0" Type="0">
        <ScreenPos x="200" y="200">
          <FlyTrack name="波浪形" degree="322.3747" />
        </ScreenPos>
      </Note>
      <Note Bar="10" BeatPos="48" Track="0" Type="0">
        <ScreenPos x="600" y="-50">
          <FlyTrack name="波浪形" degree="30.36102" />
        </ScreenPos>
      </Note>
      <Note Bar="11" BeatPos="16" Track="0" Type="0">
        <ScreenPos x="-600" y="-200">
          <FlyTrack name="波浪形" degree="173.1807" />
        </ScreenPos>
      </Note>
      <Note Bar="11" BeatPos="32" Track="0" Type="0">
        <ScreenPos x="-375" y="200">
          <FlyTrack name="波浪形" degree="295.6553" />
        </ScreenPos>
      </Note>
      <Note Bar="11" BeatPos="40" Track="0" Type="0">
        <ScreenPos x="-250" y="50">
          <FlyTrack name="波浪形" degree="318.7253" />
        </ScreenPos>
      </Note>
      <Note Bar="11" BeatPos="56" Track="0" Type="0">
        <ScreenPos x="425" y="200">
          <FlyTrack name="波浪形" degree="-5.013092" />
        </ScreenPos>
      </Note>
      <Note Bar="12" BeatPos="8" Track="0" Type="0">
        <ScreenPos x="625" y="-175">
          <FlyTrack name="波浪形" degree="58.82206" />
        </ScreenPos>
      </Note>
      <Note Bar="12" BeatPos="24" Track="0" Type="1" EndBar="12" EndPos="56" ID="2">
        <MoveTrack name="长按小山" degree="0" />
        <FlyTrack name="波浪形" degree="172.8289" />
        <ScreenPos x="225" y="-175" />
      </Note>
      <Note Bar="13" BeatPos="16" Track="4" Type="2" EndBar="13" EndPos="48" ID="3">
        <MoveTrack name="滑动2拍弧线" degree="213.7972" />
        <FlyTrack name="波浪形" degree="174.9144" />
        <ScreenPos x="-325" y="-150" />
      </Note>
      <Note Bar="14" BeatPos="0" Track="4" Type="0">
        <ScreenPos x="600" y="-200">
          <FlyTrack name="波浪形" degree="84.59488" />
        </ScreenPos>
      </Note>
      <Note Bar="14" BeatPos="16" Track="4" Type="0">
        <ScreenPos x="200" y="50">
          <FlyTrack name="波浪形" degree="211.7959" />
        </ScreenPos>
      </Note>
      <Note Bar="14" BeatPos="32" Track="4" Type="0">
        <ScreenPos x="-200" y="-200">
          <FlyTrack name="波浪形" degree="142.3747" />
        </ScreenPos>
      </Note>
      <Note Bar="14" BeatPos="48" Track="4" Type="0">
        <ScreenPos x="-600" y="50">
          <FlyTrack name="波浪形" degree="210.361" />
        </ScreenPos>
      </Note>
      <Note Bar="15" BeatPos="16" Track="4" Type="0">
        <ScreenPos x="600" y="200">
          <FlyTrack name="波浪形" degree="-4.909149" />
        </ScreenPos>
      </Note>
      <Note Bar="15" BeatPos="32" Track="4" Type="0">
        <ScreenPos x="375" y="-200">
          <FlyTrack name="波浪形" degree="115.6553" />
        </ScreenPos>
      </Note>
      <Note Bar="15" BeatPos="40" Track="4" Type="0">
        <ScreenPos x="250" y="-50">
          <FlyTrack name="波浪形" degree="140.8153" />
        </ScreenPos>
      </Note>
      <Note Bar="15" BeatPos="56" Track="4" Type="0">
        <ScreenPos x="-425" y="-200">
          <FlyTrack name="波浪形" degree="174.9869" />
        </ScreenPos>
      </Note>
      <Note Bar="16" BeatPos="8" Track="4" Type="0">
        <ScreenPos x="-625" y="175">
          <FlyTrack name="波浪形" degree="235.8974" />
        </ScreenPos>
      </Note>
      <Note Bar="16" BeatPos="16" Track="0" Type="0">
        <ScreenPos x="-425" y="250">
          <FlyTrack name="波浪形" degree="266.0495" />
        </ScreenPos>
      </Note>
      <Note Bar="16" BeatPos="24" Track="0" Type="1" EndBar="16" EndPos="48" ID="4">
        <MoveTrack name="长按直线1.5" degree="0" />
        <FlyTrack name="波浪形" degree="294.9365" />
        <ScreenPos x="-225" y="175" />
      </Note>
      <Note Bar="17" BeatPos="16" Track="0" Type="0">
        <ScreenPos x="600" y="-200">
          <FlyTrack name="波浪形" degree="83.69077" />
        </ScreenPos>
      </Note>
      <Note Bar="17" BeatPos="32" Track="0" Type="0">
        <ScreenPos x="200" y="-200">
          <FlyTrack name="波浪形" degree="83.80524" />
        </ScreenPos>
      </Note>
      <Note Bar="18" BeatPos="0" Track="0" Type="0">
        <ScreenPos x="-200" y="250">
          <FlyTrack name="波浪形" degree="169.5894" />
        </ScreenPos>
      </Note>
      <Note Bar="18" BeatPos="16" Track="0" Type="0">
        <ScreenPos x="200" y="75">
          <FlyTrack name="波浪形" degree="17.72745" />
        </ScreenPos>
      </Note>
      <Note Bar="18" BeatPos="32" Track="0" Type="0">
        <ScreenPos x="-200" y="-100">
          <FlyTrack name="波浪形" degree="148.1296" />
        </ScreenPos>
      </Note>
      <Note Bar="18" BeatPos="48" Track="0" Type="0">
        <ScreenPos x="200" y="-275">
          <FlyTrack name="波浪形" degree="19.73067" />
        </ScreenPos>
      </Note>
      <Note Bar="19" BeatPos="16" Track="0" Type="0">
        <ScreenPos x="-600" y="-200">
          <FlyTrack name="波浪形" degree="173.9055" />
        </ScreenPos>
      </Note>
      <Note Bar="19" BeatPos="32" Track="0" Type="0">
        <ScreenPos x="-600" y="200">
          <FlyTrack name="波浪形" degree="264.2898" />
        </ScreenPos>
      </Note>
      <Note Bar="19" BeatPos="40" Track="0" Type="0">
        <ScreenPos x="-400" y="200">
          <FlyTrack name="波浪形" degree="262.42" />
        </ScreenPos>
      </Note>
      <Note Bar="19" BeatPos="56" Track="0" Type="0">
        <ScreenPos x="600" y="200">
          <FlyTrack name="波浪形" degree="-5.047379" />
        </ScreenPos>
      </Note>
      <Note Bar="20" BeatPos="8" Track="0" Type="0">
        <ScreenPos x="200" y="-25">
          <FlyTrack name="波浪形" degree="146.5924" />
        </ScreenPos>
      </Note>
      <Note Bar="20" BeatPos="24" Track="0" Type="1" EndBar="20" EndPos="56" ID="5">
        <MoveTrack name="长按S形" degree="281.2172" />
        <FlyTrack name="波浪形" degree="24.8161" />
        <ScreenPos x="600" y="-250" />
      </Note>
      <Note Bar="21" BeatPos="16" Track="4" Type="0">
        <ScreenPos x="-600" y="200">
          <FlyTrack name="波浪形" degree="263.6908" />
        </ScreenPos>
      </Note>
      <Note Bar="21" BeatPos="32" Track="4" Type="0">
        <ScreenPos x="-200" y="200">
          <FlyTrack name="波浪形" degree="263.8052" />
        </ScreenPos>
      </Note>
      <Note Bar="22" BeatPos="0" Track="4" Type="0">
        <ScreenPos x="200" y="-300">
          <FlyTrack name="波浪形" degree="349.5894" />
        </ScreenPos>
      </Note>
      <Note Bar="22" BeatPos="16" Track="4" Type="0">
        <ScreenPos x="-200" y="-125">
          <FlyTrack name="波浪形" degree="197.7274" />
        </ScreenPos>
      </Note>
      <Note Bar="22" BeatPos="32" Track="4" Type="0">
        <ScreenPos x="200" y="50">
          <FlyTrack name="波浪形" degree="328.1296" />
        </ScreenPos>
      </Note>
      <Note Bar="22" BeatPos="48" Track="4" Type="0">
        <ScreenPos x="-200" y="225">
          <FlyTrack name="波浪形" degree="199.7307" />
        </ScreenPos>
      </Note>
      <Note Bar="23" BeatPos="16" Track="4" Type="0">
        <ScreenPos x="600" y="200">
          <FlyTrack name="波浪形" degree="353.9055" />
        </ScreenPos>
      </Note>
      <Note Bar="23" BeatPos="32" Track="4" Type="0">
        <ScreenPos x="600" y="-200">
          <FlyTrack name="波浪形" degree="84.28979" />
        </ScreenPos>
      </Note>
      <Note Bar="23" BeatPos="40" Track="4" Type="0">
        <ScreenPos x="400" y="-200">
          <FlyTrack name="波浪形" degree="82.42001" />
        </ScreenPos>
      </Note>
      <Note Bar="23" BeatPos="56" Track="0" Type="0">
        <ScreenPos x="-600" y="-200">
          <FlyTrack name="波浪形" degree="85.3708" />
        </ScreenPos>
      </Note>
      <Note Bar="24" BeatPos="8" Track="0" Type="0">
        <ScreenPos x="-200" y="-200">
          <FlyTrack name="波浪形" degree="352.468" />
        </ScreenPos>
      </Note>
      <Note Bar="24" BeatPos="16" Track="0" Type="0">
        <ScreenPos x="-200" y="0">
          <FlyTrack name="波浪形" degree="-7.248688" />
        </ScreenPos>
      </Note>
      <Note Bar="24" BeatPos="24" Track="0" Type="0">
        <ScreenPos x="-200" y="200">
          <FlyTrack name="波浪形" degree="-5.517075" />
        </ScreenPos>
      </Note>
      <Note Bar="24" BeatPos="40" Track="4" Type="2" EndBar="25" EndPos="8" ID="6">
        <MoveTrack name="滑动缠绕" degree="251.5884" />
        <FlyTrack name="波浪形" degree="-7.657654" />
        <ScreenPos x="250" y="-200" />
      </Note>
      <Note Bar="25" BeatPos="16" Track="4" Type="0">
        <ScreenPos x="-600" y="200">
          <FlyTrack name="波浪形" degree="167.7832" />
        </ScreenPos>
      </Note>
      <Note Bar="25" BeatPos="32" Track="4" Type="0">
        <ScreenPos x="-350" y="-150">
          <FlyTrack name="波浪形" degree="49.49497" />
        </ScreenPos>
      </Note>
      <Note Bar="26" BeatPos="0" Track="4" Type="0">
        <ScreenPos x="200" y="200">
          <FlyTrack name="波浪形" degree="-3.155762" />
        </ScreenPos>
      </Note>
      <Note Bar="26" BeatPos="12" Track="4" Type="0">
        <ScreenPos x="400" y="-100">
          <FlyTrack name="波浪形" degree="48.32602" />
        </ScreenPos>
      </Note>
      <Note Bar="26" BeatPos="24" Track="4" Type="0">
        <ScreenPos x="600" y="200">
          <FlyTrack name="波浪形" degree="292.4591" />
        </ScreenPos>
      </Note>
      <Note Bar="26" BeatPos="40" Track="4" Type="2" EndBar="27" EndPos="8" ID="7">
        <MoveTrack name="滑动缠绕对称" degree="116.9317" />
        <FlyTrack name="波浪形" degree="168.1244" />
        <ScreenPos x="-250" y="-200" />
      </Note>
      <Note Bar="27" BeatPos="16" Track="4" Type="0">
        <ScreenPos x="600" y="200">
          <FlyTrack name="波浪形" degree="-5.037292" />
        </ScreenPos>
      </Note>
      <Note Bar="27" BeatPos="32" Track="4" Type="0">
        <ScreenPos x="350" y="-150">
          <FlyTrack name="波浪形" degree="124.6036" />
        </ScreenPos>
      </Note>
      <Note Bar="28" BeatPos="0" Track="4" Type="0">
        <ScreenPos x="-200" y="200">
          <FlyTrack name="波浪形" degree="172.3626" />
        </ScreenPos>
      </Note>
      <Note Bar="28" BeatPos="12" Track="4" Type="0">
        <ScreenPos x="-400" y="-100">
          <FlyTrack name="波浪形" degree="116.6664" />
        </ScreenPos>
      </Note>
      <Note Bar="28" BeatPos="24" Track="4" Type="0">
        <ScreenPos x="-600" y="200">
          <FlyTrack name="波浪形" degree="-131.5724" />
        </ScreenPos>
      </Note>
      <Note Bar="28" BeatPos="40" Track="4" Type="2" EndBar="29" EndPos="8" ID="8">
        <MoveTrack name="滑动Z型" degree="359.455" />
        <FlyTrack name="波浪形" degree="348.1245" />
        <ScreenPos x="250" y="200" />
      </Note>
      <Note Bar="29" BeatPos="16" Track="4" Type="0">
        <ScreenPos x="-600" y="-200">
          <FlyTrack name="波浪形" degree="174.9627" />
        </ScreenPos>
      </Note>
      <Note Bar="29" BeatPos="32" Track="4" Type="0">
        <ScreenPos x="-350" y="150">
          <FlyTrack name="波浪形" degree="304.6036" />
        </ScreenPos>
      </Note>
      <Note Bar="30" BeatPos="0" Track="4" Type="0">
        <ScreenPos x="200" y="-200">
          <FlyTrack name="波浪形" degree="352.3626" />
        </ScreenPos>
      </Note>
      <Note Bar="30" BeatPos="12" Track="4" Type="0">
        <ScreenPos x="500" y="0">
          <FlyTrack name="波浪形" degree="319.4211" />
        </ScreenPos>
      </Note>
      <Note Bar="30" BeatPos="24" Track="4" Type="0">
        <ScreenPos x="200" y="200">
          <FlyTrack name="波浪形" degree="207.2521" />
        </ScreenPos>
      </Note>
      <Note Bar="30" BeatPos="40" Track="4" Type="2" EndBar="31" EndPos="8" ID="9">
        <MoveTrack name="滑动Z型" degree="179.455" />
        <FlyTrack name="波浪形" degree="168.1245" />
        <ScreenPos x="-250" y="-200" />
      </Note>
      <Note Bar="31" BeatPos="16" Track="4" Type="0">
        <ScreenPos x="600" y="200">
          <FlyTrack name="波浪形" degree="354.9627" />
        </ScreenPos>
      </Note>
      <Note Bar="31" BeatPos="32" Track="4" Type="0">
        <ScreenPos x="350" y="-150">
          <FlyTrack name="波浪形" degree="124.6036" />
        </ScreenPos>
      </Note>
      <Note Bar="31" BeatPos="40" Track="4" Type="0">
        <ScreenPos x="150" y="-25">
          <FlyTrack name="波浪形" degree="261.5232" />
        </ScreenPos>
      </Note>
      <Note Bar="31" BeatPos="48" Track="4" Type="0">
        <ScreenPos x="-50" y="-150">
          <FlyTrack name="波浪形" degree="81.49217" />
        </ScreenPos>
      </Note>
      <Note Bar="31" BeatPos="56" Track="4" Type="1" EndBar="32" EndPos="24" ID="10">
        <MoveTrack name="长按音符" degree="0" />
        <FlyTrack name="波浪形" degree="262.7531" />
        <ScreenPos x="-250" y="-25" />
      </Note>
      <Note Bar="33" BeatPos="0" Track="4" Type="0">
        <ScreenPos x="600" y="250">
          <FlyTrack name="波浪形" degree="8.577011" />
        </ScreenPos>
      </Note>
      <Note Bar="33" BeatPos="8" Track="4" Type="0">
        <ScreenPos x="450" y="100">
          <FlyTrack name="波浪形" degree="8.576263" />
        </ScreenPos>
      </Note>
      <Note Bar="33" BeatPos="16" Track="4" Type="0">
        <ScreenPos x="300" y="-50">
          <FlyTrack name="波浪形" degree="8.481613" />
        </ScreenPos>
      </Note>
      <Note Bar="33" BeatPos="24" Track="4" Type="0">
        <ScreenPos x="-200" y="100">
          <FlyTrack name="波浪形" degree="-170.8204" />
        </ScreenPos>
      </Note>
      <Note Bar="33" BeatPos="32" Track="4" Type="0">
        <ScreenPos x="-350" y="-50">
          <FlyTrack name="波浪形" degree="-172.2823" />
        </ScreenPos>
      </Note>
      <Note Bar="33" BeatPos="40" Track="4" Type="0">
        <ScreenPos x="-500" y="-200">
          <FlyTrack name="波浪形" degree="-173.7483" />
        </ScreenPos>
      </Note>
      <Note Bar="34" BeatPos="0" Track="4" Type="0">
        <ScreenPos x="200" y="-200">
          <FlyTrack name="波浪形" degree="-5.894241" />
        </ScreenPos>
      </Note>
      <Note Bar="34" BeatPos="16" Track="4" Type="0">
        <ScreenPos x="600" y="-200">
          <FlyTrack name="波浪形" degree="-6.912704" />
        </ScreenPos>
      </Note>
      <Note Bar="34" BeatPos="32" Track="4" Type="0">
        <ScreenPos x="600" y="150">
          <FlyTrack name="波浪形" degree="259.6286" />
        </ScreenPos>
      </Note>
      <Note Bar="34" BeatPos="40" Track="4" Type="0">
        <ScreenPos x="425" y="0">
          <FlyTrack name="波浪形" degree="80.90508" />
        </ScreenPos>
      </Note>
      <Note Bar="34" BeatPos="48" Track="4" Type="0">
        <ScreenPos x="250" y="150">
          <FlyTrack name="波浪形" degree="258.99" />
        </ScreenPos>
      </Note>
      <Note Bar="35" BeatPos="0" Track="4" Type="0">
        <ScreenPos x="-600" y="250">
          <FlyTrack name="波浪形" degree="171.423" />
        </ScreenPos>
      </Note>
      <Note Bar="35" BeatPos="8" Track="4" Type="0">
        <ScreenPos x="-450" y="100">
          <FlyTrack name="波浪形" degree="171.4237" />
        </ScreenPos>
      </Note>
      <Note Bar="35" BeatPos="16" Track="4" Type="0">
        <ScreenPos x="-300" y="-50">
          <FlyTrack name="波浪形" degree="171.5184" />
        </ScreenPos>
      </Note>
      <Note Bar="35" BeatPos="24" Track="4" Type="0">
        <ScreenPos x="200" y="100">
          <FlyTrack name="波浪形" degree="350.8204" />
        </ScreenPos>
      </Note>
      <Note Bar="35" BeatPos="32" Track="4" Type="0">
        <ScreenPos x="350" y="-50">
          <FlyTrack name="波浪形" degree="352.2823" />
        </ScreenPos>
      </Note>
      <Note Bar="35" BeatPos="40" Track="4" Type="0">
        <ScreenPos x="500" y="-200">
          <FlyTrack name="波浪形" degree="353.7483" />
        </ScreenPos>
      </Note>
      <Note Bar="36" BeatPos="0" Track="4" Type="2" EndBar="36" EndPos="40" ID="11">
        <MoveTrack name="滑动弧线对称" degree="-197.8214" />
        <FlyTrack name="波浪形" degree="172.3823" />
        <ScreenPos x="-250" y="-200" />
      </Note>
      <Note Bar="37" BeatPos="0" Track="4" Type="0">
        <ScreenPos x="500" y="150">
          <FlyTrack name="波浪形" degree="0.3119202" />
        </ScreenPos>
      </Note>
      <Note Bar="37" BeatPos="8" Track="4" Type="0">
        <ScreenPos x="350" y="-50">
          <FlyTrack name="波浪形" degree="29.71065" />
        </ScreenPos>
      </Note>
      <Note Bar="37" BeatPos="16" Track="4" Type="0">
        <ScreenPos x="150" y="-225">
          <FlyTrack name="波浪形" degree="67.91121" />
        </ScreenPos>
      </Note>
      <Note Bar="37" BeatPos="24" Track="4" Type="0">
        <ScreenPos x="-150" y="-225">
          <FlyTrack name="波浪形" degree="112.0888" />
        </ScreenPos>
      </Note>
      <Note Bar="37" BeatPos="32" Track="4" Type="0">
        <ScreenPos x="-350" y="-50">
          <FlyTrack name="波浪形" degree="150.2894" />
        </ScreenPos>
      </Note>
      <Note Bar="37" BeatPos="40" Track="4" Type="0">
        <ScreenPos x="-500" y="150">
          <FlyTrack name="波浪形" degree="179.6881" />
        </ScreenPos>
      </Note>
      <Note Bar="38" BeatPos="0" Track="4" Type="0">
        <ScreenPos x="200" y="-200">
          <FlyTrack name="波浪形" degree="-5.894241" />
        </ScreenPos>
      </Note>
      <Note Bar="38" BeatPos="16" Track="4" Type="0">
        <ScreenPos x="600" y="-200">
          <FlyTrack name="波浪形" degree="-6.605133" />
        </ScreenPos>
      </Note>
      <Note Bar="38" BeatPos="32" Track="4" Type="0">
        <ScreenPos x="600" y="150">
          <FlyTrack name="波浪形" degree="259.6286" />
        </ScreenPos>
      </Note>
      <Note Bar="38" BeatPos="40" Track="4" Type="0">
        <ScreenPos x="425" y="0">
          <FlyTrack name="波浪形" degree="80.90508" />
        </ScreenPos>
      </Note>
      <Note Bar="38" BeatPos="48" Track="4" Type="0">
        <ScreenPos x="250" y="150">
          <FlyTrack name="波浪形" degree="258.99" />
        </ScreenPos>
      </Note>
      <Note Bar="39" BeatPos="0" Track="4" Type="0">
        <ScreenPos x="-500" y="150">
          <FlyTrack name="波浪形" degree="175.7064" />
        </ScreenPos>
      </Note>
      <Note Bar="39" BeatPos="8" Track="4" Type="0">
        <ScreenPos x="-350" y="-50">
          <FlyTrack name="波浪形" degree="143.1503" />
        </ScreenPos>
      </Note>
      <Note Bar="39" BeatPos="16" Track="4" Type="0">
        <ScreenPos x="-150" y="-225">
          <FlyTrack name="波浪形" degree="109.1431" />
        </ScreenPos>
      </Note>
      <Note Bar="39" BeatPos="24" Track="4" Type="0">
        <ScreenPos x="150" y="-225">
          <FlyTrack name="波浪形" degree="64.68199" />
        </ScreenPos>
      </Note>
      <Note Bar="39" BeatPos="32" Track="4" Type="0">
        <ScreenPos x="350" y="-50">
          <FlyTrack name="波浪形" degree="30.83772" />
        </ScreenPos>
      </Note>
      <Note Bar="39" BeatPos="40" Track="4" Type="0">
        <ScreenPos x="500" y="150">
          <FlyTrack name="波浪形" degree="-357.5149" />
        </ScreenPos>
      </Note>
      <Note Bar="40" BeatPos="0" Track="4" Type="2" EndBar="40" EndPos="40" ID="12">
        <MoveTrack name="滑动弧线" degree="-18.00832" />
        <FlyTrack name="波浪形" degree="174.8659" />
        <ScreenPos x="-300" y="200" />
      </Note>
      <Note Bar="40" BeatPos="48" Track="4" Type="0">
        <ScreenPos x="200" y="200">
          <FlyTrack name="波浪形" degree="-5.811142" />
        </ScreenPos>
      </Note>
      <Note Bar="41" BeatPos="0" Track="4" Type="1" EndBar="41" EndPos="16" ID="13">
        <MoveTrack name="长按直线2" degree="45" />
        <FlyTrack name="波浪形" degree="171.0033" />
        <ScreenPos x="-200" y="200" />
      </Note>
      <Note Bar="41" BeatPos="24" Track="4" Type="0">
        <ScreenPos x="600" y="-200">
          <FlyTrack name="波浪形" degree="84.36317" />
        </ScreenPos>
      </Note>
      <Note Bar="41" BeatPos="32" Track="4" Type="1" EndBar="42" EndPos="32" ID="14">
        <MoveTrack name="长按卷卷" degree="-144.0084" />
        <FlyTrack name="波浪形" degree="85.31863" />
        <ScreenPos x="400" y="-200" />
      </Note>
      <Note Bar="42" BeatPos="48" Track="4" Type="0">
        <ScreenPos x="-200" y="200">
          <FlyTrack name="波浪形" degree="171.9182" />
        </ScreenPos>
      </Note>
      <Note Bar="43" BeatPos="0" Track="4" Type="1" EndBar="43" EndPos="16" ID="15">
        <MoveTrack name="长按直线2" degree="135" />
        <FlyTrack name="波浪形" degree="-8.187088" />
        <ScreenPos x="200" y="200" />
      </Note>
      <Note Bar="43" BeatPos="24" Track="4" Type="0">
        <ScreenPos x="-600" y="-200">
          <FlyTrack name="波浪形" degree="81.86482" />
        </ScreenPos>
      </Note>
      <Note Bar="43" BeatPos="32" Track="4" Type="1" EndBar="44" EndPos="0" ID="16">
        <MoveTrack name="长按小山" degree="180" />
        <FlyTrack name="波浪形" degree="82.72061" />
        <ScreenPos x="-400" y="-200" />
      </Note>
      <Note Bar="44" BeatPos="32" Track="4" Type="0">
        <ScreenPos x="600" y="200">
          <FlyTrack name="波浪形" degree="263.9905" />
        </ScreenPos>
      </Note>
      <Note Bar="44" BeatPos="40" Track="4" Type="0">
        <ScreenPos x="400" y="100">
          <FlyTrack name="波浪形" degree="260.6748" />
        </ScreenPos>
      </Note>
      <Note Bar="44" BeatPos="48" Track="4" Type="0">
        <ScreenPos x="200" y="0">
          <FlyTrack name="波浪形" degree="261.011" />
        </ScreenPos>
      </Note>
      <Note Bar="51" BeatPos="0" Track="0" Type="2" EndBar="51" EndPos="48" ID="17">
        <MoveTrack name="滑动M型" degree="0" />
        <FlyTrack name="波浪形" degree="172.4695" />
        <ScreenPos x="-300" y="200" />
      </Note>
      <Note Bar="52" BeatPos="0" Track="0" Type="0">
        <ScreenPos x="600" y="-175">
          <FlyTrack name="波浪形" degree="-7.557678" />
        </ScreenPos>
      </Note>
      <Note Bar="52" BeatPos="16" Track="0" Type="0">
        <ScreenPos x="400" y="200">
          <FlyTrack name="波浪形" degree="235.8741" />
        </ScreenPos>
      </Note>
      <Note Bar="52" BeatPos="32" Track="0" Type="0">
        <ScreenPos x="200" y="-175">
          <FlyTrack name="波浪形" degree="108.9363" />
        </ScreenPos>
      </Note>
      <Note Bar="52" BeatPos="48" Track="0" Type="0">
        <ScreenPos x="-450" y="-200">
          <FlyTrack name="波浪形" degree="174.5371" />
        </ScreenPos>
      </Note>
      <Note Bar="52" BeatPos="56" Track="0" Type="0">
        <ScreenPos x="-450" y="0">
          <FlyTrack name="波浪形" degree="174.9435" />
        </ScreenPos>
      </Note>
      <Note Bar="53" BeatPos="16" Track="1" Type="0">
        <ScreenPos x="600" y="200">
          <FlyTrack name="波浪形" degree="-4.051453" />
        </ScreenPos>
      </Note>
      <Note Bar="53" BeatPos="32" Track="1" Type="0">
        <ScreenPos x="350" y="-150">
          <FlyTrack name="波浪形" degree="121.8874" />
        </ScreenPos>
      </Note>
      <Note Bar="54" BeatPos="0" Track="1" Type="0">
        <ScreenPos x="-200" y="200">
          <FlyTrack name="波浪形" degree="174.2492" />
        </ScreenPos>
      </Note>
      <Note Bar="54" BeatPos="12" Track="1" Type="0">
        <ScreenPos x="-400" y="-100">
          <FlyTrack name="波浪形" degree="114.4553" />
        </ScreenPos>
      </Note>
      <Note Bar="54" BeatPos="24" Track="1" Type="0">
        <ScreenPos x="-600" y="200">
          <FlyTrack name="波浪形" degree="-133.3033" />
        </ScreenPos>
      </Note>
      <Note Bar="54" BeatPos="48" Track="3" Type="0">
        <ScreenPos x="450" y="-200">
          <FlyTrack name="波浪形" degree="351.3994" />
        </ScreenPos>
      </Note>
      <Note Bar="54" BeatPos="56" Track="3" Type="0">
        <ScreenPos x="450" y="0">
          <FlyTrack name="波浪形" degree="-6.839462" />
        </ScreenPos>
      </Note>
      <Note Bar="55" BeatPos="16" Track="1" Type="0">
        <ScreenPos x="-600" y="200">
          <FlyTrack name="波浪形" degree="173.4369" />
        </ScreenPos>
      </Note>
      <Note Bar="55" BeatPos="32" Track="1" Type="0">
        <ScreenPos x="-350" y="-150">
          <FlyTrack name="波浪形" degree="47.38488" />
        </ScreenPos>
      </Note>
      <Note Bar="56" BeatPos="0" Track="1" Type="0">
        <ScreenPos x="200" y="200">
          <FlyTrack name="波浪形" degree="-8.501144" />
        </ScreenPos>
      </Note>
      <Note Bar="56" BeatPos="12" Track="1" Type="0">
        <ScreenPos x="400" y="-100">
          <FlyTrack name="波浪形" degree="46.49763" />
        </ScreenPos>
      </Note>
      <Note Bar="56" BeatPos="24" Track="1" Type="0">
        <ScreenPos x="600" y="200">
          <FlyTrack name="波浪形" degree="292.7982" />
        </ScreenPos>
      </Note>
      <Note Bar="56" BeatPos="48" Track="0" Type="0">
        <ScreenPos x="-575" y="200">
          <FlyTrack name="波浪形" degree="261.8101" />
        </ScreenPos>
      </Note>
      <Note Bar="56" BeatPos="56" Track="0" Type="0">
        <ScreenPos x="-375" y="200">
          <FlyTrack name="波浪形" degree="263.5825" />
        </ScreenPos>
      </Note>
      <Note Bar="57" BeatPos="16" Track="1" Type="0">
        <ScreenPos x="600" y="-200">
          <FlyTrack name="波浪形" degree="353.2565" />
        </ScreenPos>
      </Note>
      <Note Bar="57" BeatPos="32" Track="1" Type="0">
        <ScreenPos x="350" y="150">
          <FlyTrack name="波浪形" degree="-131.2109" />
        </ScreenPos>
      </Note>
      <Note Bar="58" BeatPos="0" Track="1" Type="0">
        <ScreenPos x="-200" y="-200">
          <FlyTrack name="波浪形" degree="-187.1953" />
        </ScreenPos>
      </Note>
      <Note Bar="58" BeatPos="12" Track="1" Type="0">
        <ScreenPos x="-500" y="0">
          <FlyTrack name="波浪形" degree="-153.5465" />
        </ScreenPos>
      </Note>
      <Note Bar="58" BeatPos="24" Track="1" Type="0">
        <ScreenPos x="-200" y="200">
          <FlyTrack name="波浪形" degree="-40.50043" />
        </ScreenPos>
      </Note>
      <Note Bar="58" BeatPos="48" Track="3" Type="0">
        <ScreenPos x="575" y="200">
          <FlyTrack name="波浪形" degree="-98.68932" />
        </ScreenPos>
      </Note>
      <Note Bar="58" BeatPos="56" Track="3" Type="0">
        <ScreenPos x="375" y="200">
          <FlyTrack name="波浪形" degree="-98.79828" />
        </ScreenPos>
      </Note>
      <Note Bar="59" BeatPos="16" Track="1" Type="0">
        <ScreenPos x="-600" y="200">
          <FlyTrack name="波浪形" degree="-185.8261" />
        </ScreenPos>
      </Note>
      <Note Bar="59" BeatPos="32" Track="1" Type="0">
        <ScreenPos x="-350" y="-150">
          <FlyTrack name="波浪形" degree="-312.1461" />
        </ScreenPos>
      </Note>
      <Note Bar="59" BeatPos="40" Track="1" Type="0">
        <ScreenPos x="-150" y="-25">
          <FlyTrack name="波浪形" degree="-98.04685" />
        </ScreenPos>
      </Note>
      <Note Bar="59" BeatPos="48" Track="1" Type="0">
        <ScreenPos x="50" y="-150">
          <FlyTrack name="波浪形" degree="81.46548" />
        </ScreenPos>
      </Note>
      <Note Bar="59" BeatPos="56" Track="1" Type="1" EndBar="60" EndPos="40" ID="18">
        <MoveTrack name="长按问号" degree="46.37353" />
        <FlyTrack name="波浪形" degree="-96.60416" />
        <ScreenPos x="250" y="-25" />
      </Note>
      <Note Bar="61" BeatPos="0" Track="4" Type="0">
        <ScreenPos x="-600" y="200">
          <FlyTrack name="波浪形" degree="263.2569" />
        </ScreenPos>
      </Note>
      <Note Bar="61" BeatPos="16" Track="4" Type="0">
        <ScreenPos x="-200" y="0">
          <FlyTrack name="波浪形" degree="25.07474" />
        </ScreenPos>
      </Note>
      <Note Bar="61" BeatPos="32" Track="4" Type="0">
        <ScreenPos x="200" y="200">
          <FlyTrack name="波浪形" degree="327.2599" />
        </ScreenPos>
      </Note>
      <Note Bar="62" BeatPos="0" Track="4" Type="0">
        <ScreenPos x="600" y="-200">
          <FlyTrack name="波浪形" degree="83.2569" />
        </ScreenPos>
      </Note>
      <Note Bar="62" BeatPos="16" Track="4" Type="0">
        <ScreenPos x="200" y="0">
          <FlyTrack name="波浪形" degree="205.0747" />
        </ScreenPos>
      </Note>
      <Note Bar="62" BeatPos="32" Track="4" Type="2" EndBar="62" EndPos="48" ID="19">
        <MoveTrack name="滑动1拍直线" degree="90" />
        <FlyTrack name="波浪形" degree="147.6781" />
        <ScreenPos x="-200" y="-200" />
      </Note>
      <Note Bar="63" BeatPos="0" Track="4" Type="0">
        <ScreenPos x="600" y="200">
          <FlyTrack name="波浪形" degree="-95.15281" />
        </ScreenPos>
      </Note>
      <Note Bar="63" BeatPos="16" Track="4" Type="0">
        <ScreenPos x="200" y="0">
          <FlyTrack name="波浪形" degree="148.0815" />
        </ScreenPos>
      </Note>
      <Note Bar="63" BeatPos="32" Track="4" Type="0">
        <ScreenPos x="-200" y="200">
          <FlyTrack name="波浪形" degree="-155.8462" />
        </ScreenPos>
      </Note>
      <Note Bar="64" BeatPos="0" Track="4" Type="0">
        <ScreenPos x="-600" y="-200">
          <FlyTrack name="波浪形" degree="80.1161" />
        </ScreenPos>
      </Note>
      <Note Bar="64" BeatPos="16" Track="4" Type="0">
        <ScreenPos x="-200" y="0">
          <FlyTrack name="波浪形" degree="-32.19826" />
        </ScreenPos>
      </Note>
      <Note Bar="64" BeatPos="32" Track="4" Type="1" EndBar="64" EndPos="48" ID="20">
        <MoveTrack name="长按直线2" degree="0" />
        <FlyTrack name="波浪形" degree="24.79948" />
        <ScreenPos x="200" y="-200" />
      </Note>
      <Note Bar="65" BeatPos="0" Track="4" Type="0">
        <ScreenPos x="-600" y="200">
          <FlyTrack name="波浪形" degree="263.2569" />
        </ScreenPos>
      </Note>
      <Note Bar="65" BeatPos="16" Track="4" Type="0">
        <ScreenPos x="-200" y="0">
          <FlyTrack name="波浪形" degree="25.07474" />
        </ScreenPos>
      </Note>
      <Note Bar="65" BeatPos="32" Track="4" Type="0">
        <ScreenPos x="200" y="200">
          <FlyTrack name="波浪形" degree="327.2599" />
        </ScreenPos>
      </Note>
      <Note Bar="66" BeatPos="0" Track="4" Type="0">
        <ScreenPos x="600" y="-200">
          <FlyTrack name="波浪形" degree="83.2569" />
        </ScreenPos>
      </Note>
      <Note Bar="66" BeatPos="16" Track="4" Type="0">
        <ScreenPos x="200" y="0">
          <FlyTrack name="波浪形" degree="205.0747" />
        </ScreenPos>
      </Note>
      <Note Bar="66" BeatPos="32" Track="4" Type="2" EndBar="66" EndPos="48" ID="21">
        <MoveTrack name="滑动1拍直线" degree="90" />
        <FlyTrack name="波浪形" degree="147.6781" />
        <ScreenPos x="-200" y="-200" />
      </Note>
      <Note Bar="67" BeatPos="0" Track="4" Type="0">
        <ScreenPos x="600" y="200">
          <FlyTrack name="波浪形" degree="-95.15281" />
        </ScreenPos>
      </Note>
      <Note Bar="67" BeatPos="16" Track="4" Type="0">
        <ScreenPos x="200" y="0">
          <FlyTrack name="波浪形" degree="148.0815" />
        </ScreenPos>
      </Note>
      <Note Bar="67" BeatPos="32" Track="4" Type="0">
        <ScreenPos x="-200" y="200">
          <FlyTrack name="波浪形" degree="-155.8462" />
        </ScreenPos>
      </Note>
      <Note Bar="68" BeatPos="0" Track="4" Type="0">
        <ScreenPos x="-600" y="-200">
          <FlyTrack name="波浪形" degree="80.1161" />
        </ScreenPos>
      </Note>
      <Note Bar="68" BeatPos="16" Track="4" Type="0">
        <ScreenPos x="-200" y="0">
          <FlyTrack name="波浪形" degree="-32.19826" />
        </ScreenPos>
      </Note>
      <Note Bar="68" BeatPos="32" Track="4" Type="1" EndBar="68" EndPos="48" ID="22">
        <MoveTrack name="长按直线2" degree="0" />
        <FlyTrack name="波浪形" degree="24.79948" />
        <ScreenPos x="200" y="-200" />
      </Note>
      <Note Bar="69" BeatPos="0" Track="0" Type="0">
        <ScreenPos x="-600" y="250">
          <FlyTrack name="波浪形" degree="174.1736" />
        </ScreenPos>
      </Note>
      <Note Bar="69" BeatPos="8" Track="0" Type="0">
        <ScreenPos x="-450" y="100">
          <FlyTrack name="波浪形" degree="171.6803" />
        </ScreenPos>
      </Note>
      <Note Bar="69" BeatPos="16" Track="0" Type="0">
        <ScreenPos x="-300" y="-50">
          <FlyTrack name="波浪形" degree="172.8416" />
        </ScreenPos>
      </Note>
      <Note Bar="69" BeatPos="24" Track="0" Type="0">
        <ScreenPos x="200" y="100">
          <FlyTrack name="波浪形" degree="351.1285" />
        </ScreenPos>
      </Note>
      <Note Bar="69" BeatPos="32" Track="0" Type="0">
        <ScreenPos x="350" y="-50">
          <FlyTrack name="波浪形" degree="352.2823" />
        </ScreenPos>
      </Note>
      <Note Bar="69" BeatPos="40" Track="0" Type="0">
        <ScreenPos x="500" y="-200">
          <FlyTrack name="波浪形" degree="353.7483" />
        </ScreenPos>
      </Note>
      <Note Bar="70" BeatPos="0" Track="0" Type="0">
        <ScreenPos x="-200" y="-200">
          <FlyTrack name="波浪形" degree="170.7946" />
        </ScreenPos>
      </Note>
      <Note Bar="70" BeatPos="16" Track="0" Type="0">
        <ScreenPos x="-600" y="-200">
          <FlyTrack name="波浪形" degree="171.3448" />
        </ScreenPos>
      </Note>
      <Note Bar="70" BeatPos="32" Track="0" Type="0">
        <ScreenPos x="-600" y="150">
          <FlyTrack name="波浪形" degree="-101.5921" />
        </ScreenPos>
      </Note>
      <Note Bar="70" BeatPos="40" Track="0" Type="0">
        <ScreenPos x="-425" y="0">
          <FlyTrack name="波浪形" degree="84.34788" />
        </ScreenPos>
      </Note>
      <Note Bar="70" BeatPos="48" Track="0" Type="0">
        <ScreenPos x="-250" y="150">
          <FlyTrack name="波浪形" degree="-96.57061" />
        </ScreenPos>
      </Note>
      <Note Bar="71" BeatPos="0" Track="0" Type="0">
        <ScreenPos x="600" y="250">
          <FlyTrack name="波浪形" degree="-4.285934" />
        </ScreenPos>
      </Note>
      <Note Bar="71" BeatPos="8" Track="0" Type="0">
        <ScreenPos x="450" y="100">
          <FlyTrack name="波浪形" degree="-4.15712" />
        </ScreenPos>
      </Note>
      <Note Bar="71" BeatPos="16" Track="0" Type="0">
        <ScreenPos x="300" y="-50">
          <FlyTrack name="波浪形" degree="351.3638" />
        </ScreenPos>
      </Note>
      <Note Bar="71" BeatPos="24" Track="0" Type="0">
        <ScreenPos x="-200" y="100">
          <FlyTrack name="波浪形" degree="-189.385" />
        </ScreenPos>
      </Note>
      <Note Bar="71" BeatPos="32" Track="0" Type="0">
        <ScreenPos x="-350" y="-50">
          <FlyTrack name="波浪形" degree="-187.0263" />
        </ScreenPos>
      </Note>
      <Note Bar="71" BeatPos="40" Track="0" Type="0">
        <ScreenPos x="-500" y="-200">
          <FlyTrack name="波浪形" degree="-186.6286" />
        </ScreenPos>
      </Note>
      <Note Bar="72" BeatPos="0" Track="0" Type="2" EndBar="72" EndPos="40" ID="23">
        <MoveTrack name="滑动弧线" degree="187.7447" />
        <FlyTrack name="波浪形" degree="353.748" />
        <ScreenPos x="250" y="-200" />
      </Note>
      <Note Bar="73" BeatPos="0" Track="0" Type="0">
        <ScreenPos x="-500" y="150">
          <FlyTrack name="波浪形" degree="172.9485" />
        </ScreenPos>
      </Note>
      <Note Bar="73" BeatPos="8" Track="0" Type="0">
        <ScreenPos x="-350" y="-50">
          <FlyTrack name="波浪形" degree="143.7164" />
        </ScreenPos>
      </Note>
      <Note Bar="73" BeatPos="16" Track="0" Type="0">
        <ScreenPos x="-150" y="-225">
          <FlyTrack name="波浪形" degree="106.6674" />
        </ScreenPos>
      </Note>
      <Note Bar="73" BeatPos="24" Track="0" Type="0">
        <ScreenPos x="150" y="-225">
          <FlyTrack name="波浪形" degree="63.69201" />
        </ScreenPos>
      </Note>
      <Note Bar="73" BeatPos="32" Track="0" Type="0">
        <ScreenPos x="350" y="-50">
          <FlyTrack name="波浪形" degree="29.89152" />
        </ScreenPos>
      </Note>
      <Note Bar="73" BeatPos="40" Track="0" Type="0">
        <ScreenPos x="500" y="150">
          <FlyTrack name="波浪形" degree="-0.5802307" />
        </ScreenPos>
      </Note>
      <Note Bar="74" BeatPos="0" Track="0" Type="0">
        <ScreenPos x="-200" y="-200">
          <FlyTrack name="波浪形" degree="169.7384" />
        </ScreenPos>
      </Note>
      <Note Bar="74" BeatPos="16" Track="0" Type="0">
        <ScreenPos x="-600" y="-200">
          <FlyTrack name="波浪形" degree="171.029" />
        </ScreenPos>
      </Note>
      <Note Bar="74" BeatPos="32" Track="0" Type="0">
        <ScreenPos x="-600" y="150">
          <FlyTrack name="波浪形" degree="-99.54961" />
        </ScreenPos>
      </Note>
      <Note Bar="74" BeatPos="40" Track="0" Type="0">
        <ScreenPos x="-425" y="0">
          <FlyTrack name="波浪形" degree="79.33125" />
        </ScreenPos>
      </Note>
      <Note Bar="74" BeatPos="48" Track="0" Type="0">
        <ScreenPos x="-250" y="150">
          <FlyTrack name="波浪形" degree="-97.27358" />
        </ScreenPos>
      </Note>
      <Note Bar="75" BeatPos="0" Track="0" Type="0">
        <ScreenPos x="500" y="150">
          <FlyTrack name="波浪形" degree="4.293594" />
        </ScreenPos>
      </Note>
      <Note Bar="75" BeatPos="8" Track="0" Type="0">
        <ScreenPos x="350" y="-50">
          <FlyTrack name="波浪形" degree="33.40547" />
        </ScreenPos>
      </Note>
      <Note Bar="75" BeatPos="16" Track="0" Type="0">
        <ScreenPos x="150" y="-225">
          <FlyTrack name="波浪形" degree="67.71075" />
        </ScreenPos>
      </Note>
      <Note Bar="75" BeatPos="24" Track="0" Type="0">
        <ScreenPos x="-150" y="-225">
          <FlyTrack name="波浪形" degree="110.0997" />
        </ScreenPos>
      </Note>
      <Note Bar="75" BeatPos="32" Track="0" Type="0">
        <ScreenPos x="-350" y="-50">
          <FlyTrack name="波浪形" degree="140.7674" />
        </ScreenPos>
      </Note>
      <Note Bar="75" BeatPos="40" Track="0" Type="0">
        <ScreenPos x="-500" y="150">
          <FlyTrack name="波浪形" degree="172.8326" />
        </ScreenPos>
      </Note>
      <Note Bar="76" BeatPos="0" Track="0" Type="2" EndBar="76" EndPos="40" ID="24">
        <MoveTrack name="滑动弧线对称" degree="18.0083" />
        <FlyTrack name="波浪形" degree="352.3576" />
        <ScreenPos x="300" y="200" />
      </Note>
      <Note Bar="76" BeatPos="48" Track="0" Type="0">
        <ScreenPos x="-200" y="200">
          <FlyTrack name="波浪形" degree="170.2947" />
        </ScreenPos>
      </Note>
      <Note Bar="77" BeatPos="0" Track="0" Type="1" EndBar="77" EndPos="16" ID="25">
        <MoveTrack name="长按直线2" degree="135" />
        <FlyTrack name="波浪形" degree="-5.683975" />
        <ScreenPos x="200" y="200" />
      </Note>
      <Note Bar="77" BeatPos="24" Track="0" Type="0">
        <ScreenPos x="-600" y="-200">
          <FlyTrack name="波浪形" degree="84.99915" />
        </ScreenPos>
      </Note>
      <Note Bar="77" BeatPos="32" Track="0" Type="1" EndBar="78" EndPos="32" ID="26">
        <MoveTrack name="长按卷卷" degree="28.16522" />
        <FlyTrack name="波浪形" degree="88.05239" />
        <ScreenPos x="-400" y="-200" />
      </Note>
      <Note Bar="78" BeatPos="48" Track="0" Type="0">
        <ScreenPos x="200" y="200">
          <FlyTrack name="波浪形" degree="-5.094986" />
        </ScreenPos>
      </Note>
      <Note Bar="79" BeatPos="0" Track="0" Type="1" EndBar="79" EndPos="16" ID="27">
        <MoveTrack name="长按直线2" degree="45" />
        <FlyTrack name="波浪形" degree="171.644" />
        <ScreenPos x="-200" y="200" />
      </Note>
      <Note Bar="79" BeatPos="24" Track="0" Type="0">
        <ScreenPos x="600" y="-200">
          <FlyTrack name="波浪形" degree="80.21212" />
        </ScreenPos>
      </Note>
      <Note Bar="79" BeatPos="32" Track="0" Type="1" EndBar="80" EndPos="16" ID="28">
        <MoveTrack name="长按Z型" degree="0" />
        <FlyTrack name="波浪形" degree="84.04082" />
        <ScreenPos x="400" y="-200" />
      </Note>
      <Note Bar="80" BeatPos="32" Track="0" Type="0">
        <ScreenPos x="-600" y="200">
          <FlyTrack name="波浪形" degree="-93.91493" />
        </ScreenPos>
      </Note>
      <Note Bar="80" BeatPos="40" Track="0" Type="0">
        <ScreenPos x="-400" y="100">
          <FlyTrack name="波浪形" degree="-95.77125" />
        </ScreenPos>
      </Note>
      <Note Bar="80" BeatPos="48" Track="0" Type="0">
        <ScreenPos x="-200" y="0">
          <FlyTrack name="波浪形" degree="-96.50597" />
        </ScreenPos>
      </Note>
      <Note Bar="81" BeatPos="0" Track="0" Type="0">
        <ScreenPos x="600" y="250">
          <FlyTrack name="波浪形" degree="-6.709702" />
        </ScreenPos>
      </Note>
      <Note Bar="81" BeatPos="12" Track="0" Type="0">
        <ScreenPos x="375" y="-25">
          <FlyTrack name="波浪形" degree="116.9995" />
        </ScreenPos>
      </Note>
      <Note Bar="81" BeatPos="24" Track="0" Type="2" EndBar="81" EndPos="40" ID="29">
        <MoveTrack name="滑动弧对称" degree="0" />
        <FlyTrack name="波浪形" degree="120.5983" />
        <ScreenPos x="150" y="-300" />
      </Note>
      <Note Bar="82" BeatPos="0" Track="4" Type="0">
        <ScreenPos x="-600" y="250">
          <FlyTrack name="波浪形" degree="170.9995" />
        </ScreenPos>
      </Note>
      <Note Bar="82" BeatPos="12" Track="4" Type="0">
        <ScreenPos x="-375" y="-25">
          <FlyTrack name="波浪形" degree="42.81559" />
        </ScreenPos>
      </Note>
      <Note Bar="82" BeatPos="24" Track="4" Type="2" EndBar="82" EndPos="40" ID="30">
        <MoveTrack name="滑动弧" degree="180" />
        <FlyTrack name="波浪形" degree="41.70741" />
        <ScreenPos x="-150" y="-300" />
      </Note>
      <Note Bar="83" BeatPos="0" Track="0" Type="0">
        <ScreenPos x="625" y="200">
          <FlyTrack name="波浪形" degree="-6.263428" />
        </ScreenPos>
      </Note>
      <Note Bar="83" BeatPos="12" Track="0" Type="0">
        <ScreenPos x="450" y="-125">
          <FlyTrack name="波浪形" degree="112.3421" />
        </ScreenPos>
      </Note>
      <Note Bar="83" BeatPos="24" Track="0" Type="2" EndBar="83" EndPos="40" ID="31">
        <MoveTrack name="滑动弧对称" degree="130.4631" />
        <FlyTrack name="波浪形" degree="232.7922" />
        <ScreenPos x="250" y="200" />
      </Note>
      <Note Bar="84" BeatPos="0" Track="4" Type="0">
        <ScreenPos x="-625" y="200">
          <FlyTrack name="波浪形" degree="170.3343" />
        </ScreenPos>
      </Note>
      <Note Bar="84" BeatPos="12" Track="4" Type="0">
        <ScreenPos x="-450" y="-125">
          <FlyTrack name="波浪形" degree="49.72198" />
        </ScreenPos>
      </Note>
      <Note Bar="84" BeatPos="24" Track="4" Type="2" EndBar="84" EndPos="40" ID="32">
        <MoveTrack name="滑动弧" degree="49.81033" />
        <FlyTrack name="波浪形" degree="-66.7608" />
        <ScreenPos x="-250" y="200" />
      </Note>
    </Normal>
  </NoteInfo>
  <ActionSeq type="1">
    <ActionList start_bar="9" dance_len="1" seq_len="4" level="2" type="" />
    <ActionList start_bar="13" dance_len="2" seq_len="4" level="2" type="" />
    <ActionList start_bar="17" dance_len="2" seq_len="4" level="2" type="" />
    <ActionList start_bar="21" dance_len="2" seq_len="4" level="2" type="" />
    <ActionList start_bar="25" dance_len="2" seq_len="4" level="2" type="" />
    <ActionList start_bar="29" dance_len="2" seq_len="4" level="2" type="" />
    <ActionList start_bar="33" dance_len="2" seq_len="8" level="2" type="" />
    <ActionList start_bar="41" dance_len="2" seq_len="4" level="2" type="" />
    <ActionList start_bar="45" dance_len="4" seq_len="4" level="2" type="" />
    <ActionList start_bar="49" dance_len="1" seq_len="4" level="2" type="" />
    <ActionList start_bar="53" dance_len="2" seq_len="4" level="2" type="" />
    <ActionList start_bar="57" dance_len="2" seq_len="4" level="2" type="" />
    <ActionList start_bar="61" dance_len="2" seq_len="4" level="2" type="" />
    <ActionList start_bar="65" dance_len="2" seq_len="4" level="2" type="" />
    <ActionList start_bar="69" dance_len="2" seq_len="8" level="2" type="" />
    <ActionList start_bar="77" dance_len="2" seq_len="4" level="2" type="" />
    <ActionList start_bar="81" dance_len="2" seq_len="4" level="2" type="" />
    <ActionList start_bar="85" dance_len="4" seq_len="4" level="2" type="" />
  </ActionSeq>
  <CameraSeq>
    <Camera name="NL" bar="9" pos="0" end_bar="11" end_pos="0" />
    <Camera name="SR" bar="11" pos="0" end_bar="13" end_pos="0" />
    <Camera name="YAOBI_RL_01" bar="13" pos="0" end_bar="15" end_pos="0" />
    <Camera name="YAOBI_UD_CENTER" bar="15" pos="0" end_bar="17" end_pos="0" />
    <Camera name="NR" bar="17" pos="0" end_bar="19" end_pos="0" />
    <Camera name="SL" bar="19" pos="0" end_bar="21" end_pos="0" />
    <Camera name="T_LR_01" bar="21" pos="0" end_bar="23" end_pos="0" />
    <Camera name="YAOBI_UD_CENTER" bar="23" pos="0" end_bar="25" end_pos="0" />
    <Camera name="NR" bar="25" pos="0" end_bar="26" end_pos="0" />
    <Camera name="SL" bar="26" pos="0" end_bar="27" end_pos="0" />
    <Camera name="TL" bar="27" pos="0" end_bar="28" end_pos="0" />
    <Camera name="SR" bar="28" pos="0" end_bar="29" end_pos="0" />
    <Camera name="NC" bar="29" pos="0" end_bar="30" end_pos="0" />
    <Camera name="FC" bar="30" pos="0" end_bar="31" end_pos="0" />
    <Camera name="YAOBI_NF_07" bar="31" pos="0" end_bar="33" end_pos="0" />
    <Camera name="YAOBI_LR_02" bar="33" pos="0" end_bar="35" end_pos="0" />
    <Camera name="YAOBI_NF_01" bar="35" pos="0" end_bar="37" end_pos="0" />
    <Camera name="NR" bar="37" pos="0" end_bar="38" end_pos="0" />
    <Camera name="SR" bar="38" pos="0" end_bar="39" end_pos="0" />
    <Camera name="YAOBI_NF_06" bar="39" pos="0" end_bar="41" end_pos="0" />
    <Camera name="YAOBI_RL_05" bar="41" pos="0" end_bar="45" end_pos="0" />
    <Camera name="NC" bar="45" pos="0" end_bar="49" end_pos="0" />
    <Camera name="YAOBI_LR_09" bar="49" pos="0" end_bar="53" end_pos="0" />
    <Camera name="BL" bar="53" pos="0" end_bar="54" end_pos="0" />
    <Camera name="NC" bar="54" pos="0" end_bar="55" end_pos="0" />
    <Camera name="BR" bar="55" pos="0" end_bar="56" end_pos="0" />
    <Camera name="FC" bar="56" pos="0" end_bar="57" end_pos="0" />
    <Camera name="NR" bar="57" pos="0" end_bar="58" end_pos="0" />
    <Camera name="SR" bar="58" pos="0" end_bar="59" end_pos="0" />
    <Camera name="YAOBI_NF_06" bar="59" pos="0" end_bar="61" end_pos="0" />
    <Camera name="FC" bar="61" pos="0" end_bar="63" end_pos="0" />
    <Camera name="NC" bar="63" pos="0" end_bar="65" end_pos="0" />
    <Camera name="SL" bar="65" pos="0" end_bar="67" end_pos="0" />
    <Camera name="NR" bar="67" pos="0" end_bar="69" end_pos="0" />
    <Camera name="YAOBI_RL_02" bar="69" pos="0" end_bar="71" end_pos="0" />
    <Camera name="YAOBI_NF_01" bar="71" pos="0" end_bar="73" end_pos="0" />
    <Camera name="NL" bar="73" pos="0" end_bar="74" end_pos="0" />
    <Camera name="SL" bar="74" pos="0" end_bar="75" end_pos="0" />
    <Camera name="YAOBI_NF_07" bar="75" pos="0" end_bar="77" end_pos="0" />
    <Camera name="YAOBI_LR_05" bar="77" pos="0" end_bar="81" end_pos="0" />
    <Camera name="YAOBI_RL_03" bar="81" pos="0" end_bar="85" end_pos="0" />
    <Camera name="NC" bar="85" pos="0" end_bar="89" end_pos="0" />
  </CameraSeq>
  <DancerSort>
    <Bar>15</Bar>
    <Bar>17</Bar>
    <Bar>19</Bar>
    <Bar>21</Bar>
    <Bar>23</Bar>
    <Bar>25</Bar>
    <Bar>27</Bar>
    <Bar>29</Bar>
    <Bar>31</Bar>
    <Bar>33</Bar>
    <Bar>35</Bar>
    <Bar>37</Bar>
    <Bar>39</Bar>
    <Bar>41</Bar>
    <Bar>43</Bar>
    <Bar>51</Bar>
    <Bar>52</Bar>
    <Bar>53</Bar>
    <Bar>55</Bar>
    <Bar>57</Bar>
    <Bar>59</Bar>
    <Bar>61</Bar>
    <Bar>63</Bar>
    <Bar>65</Bar>
    <Bar>67</Bar>
    <Bar>69</Bar>
    <Bar>71</Bar>
    <Bar>73</Bar>
    <Bar>75</Bar>
    <Bar>77</Bar>
    <Bar>79</Bar>
    <Bar>81</Bar>
    <Bar>83</Bar>
  </DancerSort>
  <StageEffectSeq>
    <effect name="wutai_scene_global_script" bar="-1" length="-1" />
    <effect name="wutai_scene_note_biaozhun_01" bar="9" length="36" />
    <effect name="wutai_scene_note_biaozhun_01" bar="49" length="36" />
    <effect name="wutai_scene_note_biaozhun_01" bar="89" length="-1" />
  </StageEffectSeq>
</Level>