<?xml version="1.0" encoding="utf-8"?>
<Level>
  <LevelInfo>
    <BPM>106</BPM>
    <BeatPerBar>4</BeatPerBar>
    <BeatLen>16</BeatLen>
    <EnterTimeAdjust>1550</EnterTimeAdjust>
    <NotePreShow>2</NotePreShow>
    <LevelTime>158490</LevelTime>
    <BarAmount>70</BarAmount>
    <BeginBarLen>8</BeginBarLen>
    <IsFourTrack>False</IsFourTrack>
    <TrackCount>5</TrackCount>
    <LevelPreTime>4000</LevelPreTime>
  </LevelInfo>
  <MusicInfo>
    <Title>最精彩的艳遇</Title>
    <Artist>郭静</Artist>
    <FilePath>audio/bgm/102341</FilePath>
  </MusicInfo>
  <SectionSeq>
    <Section type="previous" endbar="0" mark="" param1="wutai_scene_pre_script_2" />
    <Section type="begin" startbar="1" endbar="8" mark="" param1="wutai_scene_begin_script_2" />
    <Section type="note" startbar="9" endbar="32" mark="" param1="" />
    <Section type="showtime" startbar="33" endbar="36" mark="dance" param1="" />
    <Section type="note" startbar="39" endbar="66" mark="" param1="" />
    <Section type="showtime" startbar="67" endbar="70" mark="pose_youyu" param1="" />
  </SectionSeq>
  <IndicatorResetPos PosNum="64">
    <Pos Bar="9" BeatPos="0" />
    <Pos Bar="13" BeatPos="0" />
    <Pos Bar="17" BeatPos="0" />
    <Pos Bar="21" BeatPos="0" />
    <Pos Bar="25" BeatPos="0" />
    <Pos Bar="29" BeatPos="0" />
    <Pos Bar="39" BeatPos="0" />
    <Pos Bar="41" BeatPos="0" />
    <Pos Bar="43" BeatPos="0" />
    <Pos Bar="47" BeatPos="0" />
    <Pos Bar="51" BeatPos="0" />
    <Pos Bar="55" BeatPos="0" />
    <Pos Bar="59" BeatPos="0" />
    <Pos Bar="63" BeatPos="0" />
    <Pos Bar="65" BeatPos="0" />
  </IndicatorResetPos>
  <NoteInfo>
    <Normal PosNum="64">
      <Note Bar="9" BeatPos="0" Track="0" Type="0">
        <ScreenPos x="-600" y="-200">
          <FlyTrack name="波浪形" degree="78.73416" />
        </ScreenPos>
      </Note>
      <Note Bar="9" BeatPos="32" Track="0" Type="0">
        <ScreenPos x="600" y="-200">
          <FlyTrack name="波浪形" degree="81.33382" />
        </ScreenPos>
      </Note>
      <Note Bar="10" BeatPos="0" Track="0" Type="0">
        <ScreenPos x="-200" y="200">
          <FlyTrack name="波浪形" degree="219.6899" />
        </ScreenPos>
      </Note>
      <Note Bar="10" BeatPos="16" Track="0" Type="0">
        <ScreenPos x="200" y="200">
          <FlyTrack name="波浪形" degree="307.7134" />
        </ScreenPos>
      </Note>
      <Note Bar="10" BeatPos="32" Track="0" Type="0">
        <ScreenPos x="-200" y="-200">
          <FlyTrack name="波浪形" degree="129.4753" />
        </ScreenPos>
      </Note>
      <Note Bar="10" BeatPos="48" Track="0" Type="0">
        <ScreenPos x="200" y="-200">
          <FlyTrack name="波浪形" degree="35.04024" />
        </ScreenPos>
      </Note>
      <Note Bar="11" BeatPos="0" Track="0" Type="0">
        <ScreenPos x="-600" y="0">
          <FlyTrack name="波浪形" degree="166.4264" />
        </ScreenPos>
      </Note>
      <Note Bar="11" BeatPos="32" Track="0" Type="0">
        <ScreenPos x="600" y="0">
          <FlyTrack name="波浪形" degree="0" />
        </ScreenPos>
      </Note>
      <Note Bar="12" BeatPos="0" Track="0" Type="0">
        <ScreenPos x="-600" y="200">
          <FlyTrack name="波浪形" degree="263.3015" />
        </ScreenPos>
      </Note>
      <Note Bar="12" BeatPos="16" Track="0" Type="0">
        <ScreenPos x="-200" y="200">
          <FlyTrack name="波浪形" degree="346.3501" />
        </ScreenPos>
      </Note>
      <Note Bar="12" BeatPos="24" Track="0" Type="1" EndBar="12" EndPos="40" ID="1">
        <MoveTrack name="长按弧" degree="163.0436" />
        <FlyTrack name="波浪形" degree="10.9438" />
        <ScreenPos x="-200" y="0" />
      </Note>
      <Note Bar="13" BeatPos="0" Track="0" Type="0">
        <ScreenPos x="400" y="200">
          <FlyTrack name="波浪形" degree="0" />
        </ScreenPos>
      </Note>
      <Note Bar="13" BeatPos="16" Track="0" Type="0">
        <ScreenPos x="600" y="-200">
          <FlyTrack name="波浪形" degree="50.58433" />
        </ScreenPos>
      </Note>
      <Note Bar="13" BeatPos="24" Track="0" Type="0">
        <ScreenPos x="400" y="-300">
          <FlyTrack name="波浪形" degree="83.50564" />
        </ScreenPos>
      </Note>
      <Note Bar="13" BeatPos="32" Track="0" Type="0">
        <ScreenPos x="200" y="-200">
          <FlyTrack name="波浪形" degree="113.0139" />
        </ScreenPos>
      </Note>
      <Note Bar="13" BeatPos="48" Track="0" Type="0">
        <ScreenPos x="200" y="200">
          <FlyTrack name="波浪形" degree="268.4878" />
        </ScreenPos>
      </Note>
      <Note Bar="14" BeatPos="0" Track="0" Type="0">
        <ScreenPos x="-250" y="200">
          <FlyTrack name="波浪形" degree="172.48" />
        </ScreenPos>
      </Note>
      <Note Bar="14" BeatPos="16" Track="0" Type="0">
        <ScreenPos x="-250" y="-200">
          <FlyTrack name="波浪形" degree="76.84801" />
        </ScreenPos>
      </Note>
      <Note Bar="14" BeatPos="24" Track="0" Type="0">
        <ScreenPos x="-450" y="-200">
          <FlyTrack name="波浪形" degree="108.089" />
        </ScreenPos>
      </Note>
      <Note Bar="14" BeatPos="48" Track="0" Type="0">
        <ScreenPos x="-450" y="200">
          <FlyTrack name="波浪形" degree="257.9583" />
        </ScreenPos>
      </Note>
      <Note Bar="15" BeatPos="0" Track="0" Type="0">
        <ScreenPos x="500" y="0">
          <FlyTrack name="波浪形" degree="7.260559" />
        </ScreenPos>
      </Note>
      <Note Bar="15" BeatPos="16" Track="0" Type="0">
        <ScreenPos x="200" y="-200">
          <FlyTrack name="波浪形" degree="38.01904" />
        </ScreenPos>
      </Note>
      <Note Bar="15" BeatPos="32" Track="0" Type="0">
        <ScreenPos x="-200" y="-200">
          <FlyTrack name="波浪形" degree="116.4535" />
        </ScreenPos>
      </Note>
      <Note Bar="15" BeatPos="48" Track="0" Type="0">
        <ScreenPos x="-500" y="0">
          <FlyTrack name="波浪形" degree="152.3565" />
        </ScreenPos>
      </Note>
      <Note Bar="15" BeatPos="56" Track="0" Type="1" EndBar="16" EndPos="8" ID="2">
        <MoveTrack name="长按弧" degree="0" />
        <FlyTrack name="波浪形" degree="190.6207" />
        <ScreenPos x="-450" y="200" />
      </Note>
      <Note Bar="17" BeatPos="0" Track="0" Type="0">
        <ScreenPos x="600" y="200">
          <FlyTrack name="波浪形" degree="258.7342" />
        </ScreenPos>
      </Note>
      <Note Bar="17" BeatPos="32" Track="0" Type="0">
        <ScreenPos x="-600" y="200">
          <FlyTrack name="波浪形" degree="261.3338" />
        </ScreenPos>
      </Note>
      <Note Bar="18" BeatPos="0" Track="0" Type="0">
        <ScreenPos x="200" y="-200">
          <FlyTrack name="波浪形" degree="39.68991" />
        </ScreenPos>
      </Note>
      <Note Bar="18" BeatPos="16" Track="0" Type="0">
        <ScreenPos x="-200" y="-200">
          <FlyTrack name="波浪形" degree="127.7134" />
        </ScreenPos>
      </Note>
      <Note Bar="18" BeatPos="32" Track="0" Type="0">
        <ScreenPos x="200" y="200">
          <FlyTrack name="波浪形" degree="309.4753" />
        </ScreenPos>
      </Note>
      <Note Bar="18" BeatPos="48" Track="0" Type="0">
        <ScreenPos x="-200" y="200">
          <FlyTrack name="波浪形" degree="215.0402" />
        </ScreenPos>
      </Note>
      <Note Bar="19" BeatPos="0" Track="0" Type="0">
        <ScreenPos x="600" y="0">
          <FlyTrack name="波浪形" degree="346.4264" />
        </ScreenPos>
      </Note>
      <Note Bar="19" BeatPos="32" Track="0" Type="0">
        <ScreenPos x="-600" y="0">
          <FlyTrack name="波浪形" degree="180" />
        </ScreenPos>
      </Note>
      <Note Bar="20" BeatPos="0" Track="0" Type="0">
        <ScreenPos x="600" y="-200">
          <FlyTrack name="波浪形" degree="83.30145" />
        </ScreenPos>
      </Note>
      <Note Bar="20" BeatPos="16" Track="0" Type="0">
        <ScreenPos x="200" y="-200">
          <FlyTrack name="波浪形" degree="166.3501" />
        </ScreenPos>
      </Note>
      <Note Bar="20" BeatPos="24" Track="0" Type="1" EndBar="20" EndPos="40" ID="3">
        <MoveTrack name="长按弧" degree="343.0436" />
        <FlyTrack name="波浪形" degree="190.9438" />
        <ScreenPos x="200" y="0" />
      </Note>
      <Note Bar="21" BeatPos="0" Track="0" Type="0">
        <ScreenPos x="-400" y="-200">
          <FlyTrack name="波浪形" degree="170.8928" />
        </ScreenPos>
      </Note>
      <Note Bar="21" BeatPos="16" Track="0" Type="0">
        <ScreenPos x="-600" y="200">
          <FlyTrack name="波浪形" degree="230.5843" />
        </ScreenPos>
      </Note>
      <Note Bar="21" BeatPos="24" Track="0" Type="0">
        <ScreenPos x="-400" y="300">
          <FlyTrack name="波浪形" degree="263.5056" />
        </ScreenPos>
      </Note>
      <Note Bar="21" BeatPos="32" Track="0" Type="0">
        <ScreenPos x="-200" y="200">
          <FlyTrack name="波浪形" degree="293.0139" />
        </ScreenPos>
      </Note>
      <Note Bar="21" BeatPos="48" Track="0" Type="0">
        <ScreenPos x="-200" y="-200">
          <FlyTrack name="波浪形" degree="88.48779" />
        </ScreenPos>
      </Note>
      <Note Bar="22" BeatPos="0" Track="0" Type="0">
        <ScreenPos x="250" y="-200">
          <FlyTrack name="波浪形" degree="352.48" />
        </ScreenPos>
      </Note>
      <Note Bar="22" BeatPos="16" Track="0" Type="0">
        <ScreenPos x="250" y="200">
          <FlyTrack name="波浪形" degree="256.848" />
        </ScreenPos>
      </Note>
      <Note Bar="22" BeatPos="24" Track="0" Type="0">
        <ScreenPos x="450" y="200">
          <FlyTrack name="波浪形" degree="288.089" />
        </ScreenPos>
      </Note>
      <Note Bar="22" BeatPos="48" Track="0" Type="0">
        <ScreenPos x="450" y="-200">
          <FlyTrack name="波浪形" degree="77.95834" />
        </ScreenPos>
      </Note>
      <Note Bar="23" BeatPos="0" Track="0" Type="0">
        <ScreenPos x="-500" y="0">
          <FlyTrack name="波浪形" degree="214.478" />
        </ScreenPos>
      </Note>
      <Note Bar="23" BeatPos="16" Track="0" Type="0">
        <ScreenPos x="-200" y="200">
          <FlyTrack name="波浪形" degree="316.0867" />
        </ScreenPos>
      </Note>
      <Note Bar="23" BeatPos="32" Track="0" Type="0">
        <ScreenPos x="200" y="200">
          <FlyTrack name="波浪形" degree="-5.965851" />
        </ScreenPos>
      </Note>
      <Note Bar="23" BeatPos="44" Track="0" Type="0">
        <ScreenPos x="500" y="0">
          <FlyTrack name="波浪形" degree="24.43231" />
        </ScreenPos>
      </Note>
      <Note Bar="23" BeatPos="56" Track="0" Type="0">
        <ScreenPos x="200" y="-200">
          <FlyTrack name="波浪形" degree="134.3333" />
        </ScreenPos>
      </Note>
      <Note Bar="24" BeatPos="0" Track="0" Type="1" EndBar="24" EndPos="48" ID="4">
        <MoveTrack name="长按Z型" degree="-90" />
        <FlyTrack name="波浪形" degree="129.9186" />
        <ScreenPos x="0" y="-200" />
      </Note>
      <Note Bar="25" BeatPos="0" Track="0" Type="0">
        <ScreenPos x="-600" y="200">
          <FlyTrack name="波浪形" degree="248.5989" />
        </ScreenPos>
      </Note>
      <Note Bar="25" BeatPos="8" Track="0" Type="1" EndBar="25" EndPos="24" ID="5">
        <MoveTrack name="长按弧" degree="0" />
        <FlyTrack name="波浪形" degree="272.4643" />
        <ScreenPos x="-400" y="200" />
      </Note>
      <Note Bar="25" BeatPos="32" Track="0" Type="0">
        <ScreenPos x="-200" y="-200">
          <FlyTrack name="波浪形" degree="51.99866" />
        </ScreenPos>
      </Note>
      <Note Bar="25" BeatPos="48" Track="0" Type="0">
        <ScreenPos x="0" y="200">
          <FlyTrack name="波浪形" degree="-66.39954" />
        </ScreenPos>
      </Note>
      <Note Bar="26" BeatPos="0" Track="0" Type="0">
        <ScreenPos x="200" y="-200">
          <FlyTrack name="波浪形" degree="57.94221" />
        </ScreenPos>
      </Note>
      <Note Bar="26" BeatPos="16" Track="0" Type="0">
        <ScreenPos x="600" y="-200">
          <FlyTrack name="波浪形" degree="-3.760101" />
        </ScreenPos>
      </Note>
      <Note Bar="26" BeatPos="32" Track="0" Type="2" EndBar="26" EndPos="48" ID="6">
        <MoveTrack name="滑动1拍直线" degree="-270" />
        <FlyTrack name="波浪形" degree="266.7379" />
        <ScreenPos x="600" y="200" />
      </Note>
      <Note Bar="27" BeatPos="0" Track="0" Type="0">
        <ScreenPos x="-600" y="200">
          <FlyTrack name="波浪形" degree="148.099" />
        </ScreenPos>
      </Note>
      <Note Bar="27" BeatPos="12" Track="0" Type="0">
        <ScreenPos x="-400" y="0">
          <FlyTrack name="波浪形" degree="142.8995" />
        </ScreenPos>
      </Note>
      <Note Bar="27" BeatPos="24" Track="0" Type="0">
        <ScreenPos x="-200" y="-200">
          <FlyTrack name="波浪形" degree="124.5072" />
        </ScreenPos>
      </Note>
      <Note Bar="27" BeatPos="32" Track="0" Type="0">
        <ScreenPos x="0" y="-200">
          <FlyTrack name="波浪形" degree="87.69174" />
        </ScreenPos>
      </Note>
      <Note Bar="27" BeatPos="48" Track="0" Type="0">
        <ScreenPos x="200" y="200">
          <FlyTrack name="波浪形" degree="293.2636" />
        </ScreenPos>
      </Note>
      <Note Bar="28" BeatPos="0" Track="0" Type="0">
        <ScreenPos x="-200" y="200">
          <FlyTrack name="波浪形" degree="175.3743" />
        </ScreenPos>
      </Note>
      <Note Bar="28" BeatPos="16" Track="0" Type="0">
        <ScreenPos x="-600" y="200">
          <FlyTrack name="波浪形" degree="174.5136" />
        </ScreenPos>
      </Note>
      <Note Bar="28" BeatPos="24" Track="0" Type="1" EndBar="28" EndPos="48" ID="7">
        <MoveTrack name="长按直线1.5" degree="0" />
        <FlyTrack name="波浪形" degree="144.1656" />
        <ScreenPos x="-600" y="0" />
      </Note>
      <Note Bar="29" BeatPos="0" Track="0" Type="0">
        <ScreenPos x="600" y="200">
          <FlyTrack name="波浪形" degree="264.8404" />
        </ScreenPos>
      </Note>
      <Note Bar="29" BeatPos="8" Track="0" Type="1" EndBar="29" EndPos="24" ID="8">
        <MoveTrack name="长按弧" degree="180" />
        <FlyTrack name="波浪形" degree="241.6827" />
        <ScreenPos x="400" y="200" />
      </Note>
      <Note Bar="29" BeatPos="32" Track="0" Type="0">
        <ScreenPos x="200" y="-200">
          <FlyTrack name="波浪形" degree="110.5486" />
        </ScreenPos>
      </Note>
      <Note Bar="29" BeatPos="48" Track="0" Type="0">
        <ScreenPos x="0" y="200">
          <FlyTrack name="波浪形" degree="239.8093" />
        </ScreenPos>
      </Note>
      <Note Bar="30" BeatPos="0" Track="0" Type="0">
        <ScreenPos x="-200" y="-200">
          <FlyTrack name="波浪形" degree="116.231" />
        </ScreenPos>
      </Note>
      <Note Bar="30" BeatPos="16" Track="0" Type="0">
        <ScreenPos x="-600" y="-200">
          <FlyTrack name="波浪形" degree="177.9695" />
        </ScreenPos>
      </Note>
      <Note Bar="30" BeatPos="32" Track="0" Type="0">
        <ScreenPos x="-600" y="200">
          <FlyTrack name="波浪形" degree="261.8606" />
        </ScreenPos>
      </Note>
      <Note Bar="30" BeatPos="48" Track="0" Type="0">
        <ScreenPos x="600" y="200">
          <FlyTrack name="波浪形" degree="0" />
        </ScreenPos>
      </Note>
      <Note Bar="30" BeatPos="56" Track="0" Type="0">
        <ScreenPos x="600" y="0">
          <FlyTrack name="波浪形" degree="-6.925735" />
        </ScreenPos>
      </Note>
      <Note Bar="31" BeatPos="0" Track="0" Type="0">
        <ScreenPos x="600" y="-200">
          <FlyTrack name="波浪形" degree="-2.137039" />
        </ScreenPos>
      </Note>
      <Note Bar="31" BeatPos="16" Track="0" Type="0">
        <ScreenPos x="-600" y="-200">
          <FlyTrack name="波浪形" degree="174.5705" />
        </ScreenPos>
      </Note>
      <Note Bar="31" BeatPos="32" Track="0" Type="0">
        <ScreenPos x="-600" y="200">
          <FlyTrack name="波浪形" degree="261.1995" />
        </ScreenPos>
      </Note>
      <Note Bar="31" BeatPos="48" Track="0" Type="0">
        <ScreenPos x="-200" y="200">
          <FlyTrack name="波浪形" degree="0" />
        </ScreenPos>
      </Note>
      <Note Bar="31" BeatPos="56" Track="0" Type="0">
        <ScreenPos x="-200" y="0">
          <FlyTrack name="波浪形" degree="0" />
        </ScreenPos>
      </Note>
      <Note Bar="32" BeatPos="0" Track="0" Type="1" EndBar="32" EndPos="48" ID="9">
        <MoveTrack name="长按波浪" degree="0" />
        <FlyTrack name="波浪形" degree="0" />
        <ScreenPos x="-200" y="-200" />
      </Note>
      <Note Bar="39" BeatPos="0" Track="4" Type="0">
        <ScreenPos x="-600" y="200">
          <FlyTrack name="波浪形" degree="177.863" />
        </ScreenPos>
      </Note>
      <Note Bar="39" BeatPos="16" Track="4" Type="0">
        <ScreenPos x="600" y="200">
          <FlyTrack name="波浪形" degree="354.5705" />
        </ScreenPos>
      </Note>
      <Note Bar="39" BeatPos="32" Track="4" Type="0">
        <ScreenPos x="600" y="-200">
          <FlyTrack name="波浪形" degree="81.19952" />
        </ScreenPos>
      </Note>
      <Note Bar="39" BeatPos="48" Track="4" Type="0">
        <ScreenPos x="200" y="-200">
          <FlyTrack name="波浪形" degree="180" />
        </ScreenPos>
      </Note>
      <Note Bar="39" BeatPos="56" Track="4" Type="0">
        <ScreenPos x="200" y="0">
          <FlyTrack name="波浪形" degree="180" />
        </ScreenPos>
      </Note>
      <Note Bar="40" BeatPos="0" Track="4" Type="1" EndBar="40" EndPos="48" ID="10">
        <MoveTrack name="长按波浪" degree="180" />
        <FlyTrack name="波浪形" degree="180" />
        <ScreenPos x="200" y="200" />
      </Note>
      <Note Bar="41" BeatPos="0" Track="0" Type="0">
        <ScreenPos x="-600" y="-200">
          <FlyTrack name="波浪形" degree="176.5388" />
        </ScreenPos>
      </Note>
      <Note Bar="41" BeatPos="16" Track="0" Type="0">
        <ScreenPos x="-600" y="200">
          <FlyTrack name="波浪形" degree="267.5423" />
        </ScreenPos>
      </Note>
      <Note Bar="41" BeatPos="32" Track="0" Type="0">
        <ScreenPos x="-200" y="200">
          <FlyTrack name="波浪形" degree="0" />
        </ScreenPos>
      </Note>
      <Note Bar="41" BeatPos="48" Track="0" Type="0">
        <ScreenPos x="-200" y="-200">
          <FlyTrack name="波浪形" degree="79.38803" />
        </ScreenPos>
      </Note>
      <Note Bar="42" BeatPos="0" Track="0" Type="0">
        <ScreenPos x="200" y="-200">
          <FlyTrack name="波浪形" degree="0" />
        </ScreenPos>
      </Note>
      <Note Bar="42" BeatPos="32" Track="0" Type="0">
        <ScreenPos x="-600" y="-200">
          <FlyTrack name="波浪形" degree="173.6731" />
        </ScreenPos>
      </Note>
      <Note Bar="43" BeatPos="0" Track="0" Type="0">
        <ScreenPos x="600" y="0">
          <FlyTrack name="波浪形" degree="0" />
        </ScreenPos>
      </Note>
      <Note Bar="43" BeatPos="32" Track="0" Type="0">
        <ScreenPos x="-600" y="0">
          <FlyTrack name="波浪形" degree="175.5907" />
        </ScreenPos>
      </Note>
      <Note Bar="44" BeatPos="0" Track="0" Type="0">
        <ScreenPos x="200" y="-200">
          <FlyTrack name="波浪形" degree="79.14171" />
        </ScreenPos>
      </Note>
      <Note Bar="44" BeatPos="16" Track="0" Type="0">
        <ScreenPos x="0" y="200">
          <FlyTrack name="波浪形" degree="244.4868" />
        </ScreenPos>
      </Note>
      <Note Bar="44" BeatPos="32" Track="0" Type="0">
        <ScreenPos x="-200" y="-200">
          <FlyTrack name="波浪形" degree="110.9468" />
        </ScreenPos>
      </Note>
      <Note Bar="45" BeatPos="0" Track="0" Type="0">
        <ScreenPos x="600" y="200">
          <FlyTrack name="波浪形" degree="262.5596" />
        </ScreenPos>
      </Note>
      <Note Bar="45" BeatPos="32" Track="0" Type="0">
        <ScreenPos x="-600" y="200">
          <FlyTrack name="波浪形" degree="260.8621" />
        </ScreenPos>
      </Note>
      <Note Bar="46" BeatPos="0" Track="0" Type="0">
        <ScreenPos x="600" y="-200">
          <FlyTrack name="波浪形" degree="80.77213" />
        </ScreenPos>
      </Note>
      <Note Bar="46" BeatPos="16" Track="0" Type="0">
        <ScreenPos x="200" y="-200">
          <FlyTrack name="波浪形" degree="175.7841" />
        </ScreenPos>
      </Note>
      <Note Bar="46" BeatPos="24" Track="0" Type="0">
        <ScreenPos x="200" y="0">
          <FlyTrack name="波浪形" degree="203.7331" />
        </ScreenPos>
      </Note>
      <Note Bar="47" BeatPos="0" Track="0" Type="0">
        <ScreenPos x="-600" y="0">
          <FlyTrack name="波浪形" degree="173.2763" />
        </ScreenPos>
      </Note>
      <Note Bar="47" BeatPos="32" Track="0" Type="0">
        <ScreenPos x="600" y="0">
          <FlyTrack name="波浪形" degree="0" />
        </ScreenPos>
      </Note>
      <Note Bar="48" BeatPos="0" Track="0" Type="0">
        <ScreenPos x="-200" y="-200">
          <FlyTrack name="波浪形" degree="82.21254" />
        </ScreenPos>
      </Note>
      <Note Bar="48" BeatPos="16" Track="0" Type="0">
        <ScreenPos x="0" y="200">
          <FlyTrack name="波浪形" degree="292.5947" />
        </ScreenPos>
      </Note>
      <Note Bar="48" BeatPos="32" Track="0" Type="0">
        <ScreenPos x="200" y="-200">
          <FlyTrack name="波浪形" degree="55.36227" />
        </ScreenPos>
      </Note>
      <Note Bar="49" BeatPos="0" Track="0" Type="0">
        <ScreenPos x="-600" y="200">
          <FlyTrack name="波浪形" degree="178.4109" />
        </ScreenPos>
      </Note>
      <Note Bar="49" BeatPos="16" Track="0" Type="0">
        <ScreenPos x="-600" y="-200">
          <FlyTrack name="波浪形" degree="80.52045" />
        </ScreenPos>
      </Note>
      <Note Bar="49" BeatPos="32" Track="0" Type="0">
        <ScreenPos x="-200" y="-200">
          <FlyTrack name="波浪形" degree="0" />
        </ScreenPos>
      </Note>
      <Note Bar="49" BeatPos="48" Track="0" Type="0">
        <ScreenPos x="-200" y="200">
          <FlyTrack name="波浪形" degree="259.6062" />
        </ScreenPos>
      </Note>
      <Note Bar="49" BeatPos="56" Track="0" Type="0">
        <ScreenPos x="0" y="200">
          <FlyTrack name="波浪形" degree="263.7874" />
        </ScreenPos>
      </Note>
      <Note Bar="50" BeatPos="0" Track="0" Type="1" EndBar="50" EndPos="32" ID="11">
        <MoveTrack name="长按折线" degree="180" />
        <FlyTrack name="波浪形" degree="272.9158" />
        <ScreenPos x="200" y="200" />
      </Note>
      <Note Bar="51" BeatPos="0" Track="4" Type="0">
        <ScreenPos x="600" y="-200">
          <FlyTrack name="波浪形" degree="68.59888" />
        </ScreenPos>
      </Note>
      <Note Bar="51" BeatPos="8" Track="4" Type="1" EndBar="51" EndPos="24" ID="12">
        <MoveTrack name="长按弧" degree="180" />
        <FlyTrack name="波浪形" degree="92.46429" />
        <ScreenPos x="400" y="-200" />
      </Note>
      <Note Bar="51" BeatPos="32" Track="4" Type="0">
        <ScreenPos x="200" y="200">
          <FlyTrack name="波浪形" degree="231.9987" />
        </ScreenPos>
      </Note>
      <Note Bar="51" BeatPos="48" Track="4" Type="0">
        <ScreenPos x="0" y="-200">
          <FlyTrack name="波浪形" degree="113.6005" />
        </ScreenPos>
      </Note>
      <Note Bar="52" BeatPos="0" Track="4" Type="0">
        <ScreenPos x="-200" y="200">
          <FlyTrack name="波浪形" degree="237.9422" />
        </ScreenPos>
      </Note>
      <Note Bar="52" BeatPos="16" Track="4" Type="0">
        <ScreenPos x="-600" y="200">
          <FlyTrack name="波浪形" degree="176.2399" />
        </ScreenPos>
      </Note>
      <Note Bar="52" BeatPos="32" Track="4" Type="2" EndBar="52" EndPos="48" ID="13">
        <MoveTrack name="滑动1拍直线" degree="-90" />
        <FlyTrack name="波浪形" degree="86.73785" />
        <ScreenPos x="-600" y="-200" />
      </Note>
      <Note Bar="53" BeatPos="0" Track="4" Type="0">
        <ScreenPos x="600" y="-200">
          <FlyTrack name="波浪形" degree="328.099" />
        </ScreenPos>
      </Note>
      <Note Bar="53" BeatPos="12" Track="4" Type="0">
        <ScreenPos x="400" y="0">
          <FlyTrack name="波浪形" degree="322.8995" />
        </ScreenPos>
      </Note>
      <Note Bar="53" BeatPos="24" Track="4" Type="0">
        <ScreenPos x="200" y="200">
          <FlyTrack name="波浪形" degree="304.5072" />
        </ScreenPos>
      </Note>
      <Note Bar="53" BeatPos="32" Track="4" Type="0">
        <ScreenPos x="0" y="200">
          <FlyTrack name="波浪形" degree="267.6917" />
        </ScreenPos>
      </Note>
      <Note Bar="53" BeatPos="48" Track="4" Type="0">
        <ScreenPos x="-200" y="-200">
          <FlyTrack name="波浪形" degree="113.2636" />
        </ScreenPos>
      </Note>
      <Note Bar="54" BeatPos="0" Track="4" Type="0">
        <ScreenPos x="200" y="-200">
          <FlyTrack name="波浪形" degree="355.3743" />
        </ScreenPos>
      </Note>
      <Note Bar="54" BeatPos="16" Track="4" Type="0">
        <ScreenPos x="600" y="-200">
          <FlyTrack name="波浪形" degree="354.5136" />
        </ScreenPos>
      </Note>
      <Note Bar="54" BeatPos="24" Track="4" Type="1" EndBar="54" EndPos="48" ID="14">
        <MoveTrack name="长按直线1.5" degree="180" />
        <FlyTrack name="波浪形" degree="324.1656" />
        <ScreenPos x="600" y="0" />
      </Note>
      <Note Bar="55" BeatPos="0" Track="4" Type="0">
        <ScreenPos x="-600" y="-200">
          <FlyTrack name="波浪形" degree="84.84039" />
        </ScreenPos>
      </Note>
      <Note Bar="55" BeatPos="8" Track="4" Type="1" EndBar="55" EndPos="24" ID="15">
        <MoveTrack name="长按弧" degree="360" />
        <FlyTrack name="波浪形" degree="61.68271" />
        <ScreenPos x="-400" y="-200" />
      </Note>
      <Note Bar="55" BeatPos="32" Track="4" Type="0">
        <ScreenPos x="-200" y="200">
          <FlyTrack name="波浪形" degree="290.5486" />
        </ScreenPos>
      </Note>
      <Note Bar="55" BeatPos="48" Track="4" Type="0">
        <ScreenPos x="0" y="-200">
          <FlyTrack name="波浪形" degree="59.80933" />
        </ScreenPos>
      </Note>
      <Note Bar="56" BeatPos="0" Track="4" Type="0">
        <ScreenPos x="200" y="200">
          <FlyTrack name="波浪形" degree="296.231" />
        </ScreenPos>
      </Note>
      <Note Bar="56" BeatPos="16" Track="4" Type="0">
        <ScreenPos x="600" y="200">
          <FlyTrack name="波浪形" degree="357.9695" />
        </ScreenPos>
      </Note>
      <Note Bar="56" BeatPos="32" Track="4" Type="0">
        <ScreenPos x="600" y="-200">
          <FlyTrack name="波浪形" degree="81.8606" />
        </ScreenPos>
      </Note>
      <Note Bar="56" BeatPos="48" Track="4" Type="0">
        <ScreenPos x="-600" y="-200">
          <FlyTrack name="波浪形" degree="180" />
        </ScreenPos>
      </Note>
      <Note Bar="56" BeatPos="56" Track="4" Type="0">
        <ScreenPos x="-600" y="0">
          <FlyTrack name="波浪形" degree="173.0743" />
        </ScreenPos>
      </Note>
      <Note Bar="57" BeatPos="0" Track="4" Type="0">
        <ScreenPos x="-600" y="200">
          <FlyTrack name="波浪形" degree="177.863" />
        </ScreenPos>
      </Note>
      <Note Bar="57" BeatPos="16" Track="4" Type="0">
        <ScreenPos x="600" y="200">
          <FlyTrack name="波浪形" degree="354.5705" />
        </ScreenPos>
      </Note>
      <Note Bar="57" BeatPos="32" Track="4" Type="0">
        <ScreenPos x="600" y="-200">
          <FlyTrack name="波浪形" degree="81.19952" />
        </ScreenPos>
      </Note>
      <Note Bar="57" BeatPos="48" Track="4" Type="0">
        <ScreenPos x="200" y="-200">
          <FlyTrack name="波浪形" degree="180" />
        </ScreenPos>
      </Note>
      <Note Bar="57" BeatPos="56" Track="4" Type="0">
        <ScreenPos x="200" y="0">
          <FlyTrack name="波浪形" degree="180" />
        </ScreenPos>
      </Note>
      <Note Bar="58" BeatPos="0" Track="4" Type="1" EndBar="58" EndPos="48" ID="16">
        <MoveTrack name="长按波浪" degree="180" />
        <FlyTrack name="波浪形" degree="180" />
        <ScreenPos x="200" y="200" />
      </Note>
      <Note Bar="59" BeatPos="0" Track="0" Type="0">
        <ScreenPos x="-600" y="200">
          <FlyTrack name="波浪形" degree="171.7995" />
        </ScreenPos>
      </Note>
      <Note Bar="59" BeatPos="32" Track="0" Type="0">
        <ScreenPos x="0" y="-200">
          <FlyTrack name="波浪形" degree="28.43159" />
        </ScreenPos>
      </Note>
      <Note Bar="60" BeatPos="0" Track="0" Type="1" EndBar="60" EndPos="32" ID="17">
        <MoveTrack name="长按波浪2拍" degree="90" />
        <FlyTrack name="波浪形" degree="305.4213" />
        <ScreenPos x="600" y="200" />
      </Note>
      <Note Bar="60" BeatPos="48" Track="0" Type="0">
        <ScreenPos x="-600" y="200">
          <FlyTrack name="波浪形" degree="173.5315" />
        </ScreenPos>
      </Note>
      <Note Bar="61" BeatPos="0" Track="0" Type="1" EndBar="61" EndPos="48" ID="18">
        <MoveTrack name="长按波浪" degree="0" />
        <FlyTrack name="波浪形" degree="80.60293" />
        <ScreenPos x="-600" y="-200" />
      </Note>
      <Note Bar="62" BeatPos="0" Track="0" Type="1" EndBar="62" EndPos="48" ID="19">
        <MoveTrack name="长按波浪" degree="180" />
        <FlyTrack name="波浪形" degree="82.01244" />
        <ScreenPos x="600" y="-200" />
      </Note>
      <Note Bar="63" BeatPos="0" Track="0" Type="0">
        <ScreenPos x="-600" y="200">
          <FlyTrack name="波浪形" degree="161.0036" />
        </ScreenPos>
      </Note>
      <Note Bar="63" BeatPos="16" Track="0" Type="0">
        <ScreenPos x="-600" y="-200">
          <FlyTrack name="波浪形" degree="85.17908" />
        </ScreenPos>
      </Note>
      <Note Bar="63" BeatPos="24" Track="0" Type="0">
        <ScreenPos x="-400" y="-200">
          <FlyTrack name="波浪形" degree="56.25599" />
        </ScreenPos>
      </Note>
      <Note Bar="63" BeatPos="48" Track="0" Type="0">
        <ScreenPos x="-400" y="200">
          <FlyTrack name="波浪形" degree="259.3275" />
        </ScreenPos>
      </Note>
      <Note Bar="64" BeatPos="0" Track="0" Type="0">
        <ScreenPos x="0" y="200">
          <FlyTrack name="波浪形" degree="0" />
        </ScreenPos>
      </Note>
      <Note Bar="64" BeatPos="16" Track="0" Type="0">
        <ScreenPos x="0" y="-200">
          <FlyTrack name="波浪形" degree="80.71686" />
        </ScreenPos>
      </Note>
      <Note Bar="64" BeatPos="24" Track="0" Type="0">
        <ScreenPos x="200" y="-200">
          <FlyTrack name="波浪形" degree="58.06289" />
        </ScreenPos>
      </Note>
      <Note Bar="65" BeatPos="0" Track="0" Type="0">
        <ScreenPos x="600" y="200">
          <FlyTrack name="波浪形" degree="1.085678" />
        </ScreenPos>
      </Note>
      <Note Bar="65" BeatPos="16" Track="0" Type="0">
        <ScreenPos x="600" y="-200">
          <FlyTrack name="波浪形" degree="81.28434" />
        </ScreenPos>
      </Note>
      <Note Bar="65" BeatPos="24" Track="0" Type="0">
        <ScreenPos x="400" y="-200">
          <FlyTrack name="波浪形" degree="111.2901" />
        </ScreenPos>
      </Note>
      <Note Bar="65" BeatPos="48" Track="0" Type="0">
        <ScreenPos x="400" y="200">
          <FlyTrack name="波浪形" degree="-92.49342" />
        </ScreenPos>
      </Note>
      <Note Bar="66" BeatPos="0" Track="0" Type="0">
        <ScreenPos x="0" y="200">
          <FlyTrack name="波浪形" degree="171.1991" />
        </ScreenPos>
      </Note>
      <Note Bar="66" BeatPos="16" Track="0" Type="0">
        <ScreenPos x="0" y="-200">
          <FlyTrack name="波浪形" degree="83.22993" />
        </ScreenPos>
      </Note>
      <Note Bar="66" BeatPos="24" Track="0" Type="0">
        <ScreenPos x="-200" y="-200">
          <FlyTrack name="波浪形" degree="113.4023" />
        </ScreenPos>
      </Note>
    </Normal>
  </NoteInfo>
  <ActionSeq type="1">
    <ActionList start_bar="9" dance_len="1" seq_len="4" level="2" type="" />
    <ActionList start_bar="13" dance_len="2" seq_len="4" level="2" type="" />
    <ActionList start_bar="17" dance_len="2" seq_len="4" level="2" type="" />
    <ActionList start_bar="21" dance_len="2" seq_len="4" level="2" type="" />
    <ActionList start_bar="25" dance_len="2" seq_len="8" level="2" type="" />
    <ActionList start_bar="33" dance_len="4" seq_len="4" level="2" type="" />
    <ActionList start_bar="37" dance_len="1" seq_len="4" level="2" type="" />
    <ActionList start_bar="41" dance_len="2" seq_len="2" level="2" type="" />
    <ActionList start_bar="43" dance_len="2" seq_len="4" level="2" type="" />
    <ActionList start_bar="47" dance_len="2" seq_len="4" level="2" type="" />
    <ActionList start_bar="51" dance_len="2" seq_len="8" level="2" type="" />
    <ActionList start_bar="59" dance_len="2" seq_len="4" level="2" type="" />
    <ActionList start_bar="63" dance_len="2" seq_len="4" level="2" type="" />
    <ActionList start_bar="67" dance_len="4" seq_len="4" level="2" type="" />
  </ActionSeq>
  <CameraSeq>
    <Camera name="SL" bar="9" pos="0" end_bar="11" end_pos="0" />
    <Camera name="NR" bar="11" pos="0" end_bar="13" end_pos="0" />
    <Camera name="YAOBI_RL_04" bar="13" pos="0" end_bar="17" end_pos="0" />
    <Camera name="BR" bar="17" pos="0" end_bar="19" end_pos="0" />
    <Camera name="SC" bar="19" pos="0" end_bar="21" end_pos="0" />
    <Camera name="YAOBI_LR_07" bar="21" pos="0" end_bar="25" end_pos="0" />
    <Camera name="YAOBI_RL_06" bar="25" pos="0" end_bar="29" end_pos="0" />
    <Camera name="YAOBI_LR_12" bar="29" pos="0" end_bar="33" end_pos="0" />
    <Camera name="FC" bar="33" pos="0" end_bar="37" end_pos="0" />
    <Camera name="YAOBI_FN_01" bar="37" pos="0" end_bar="41" end_pos="0" />
    <Camera name="SR" bar="41" pos="0" end_bar="43" end_pos="0" />
    <Camera name="NR" bar="43" pos="0" end_bar="45" end_pos="0" />
    <Camera name="BL_U" bar="45" pos="0" end_bar="47" end_pos="0" />
    <Camera name="YAOBI_RL_07" bar="47" pos="0" end_bar="51" end_pos="0" />
    <Camera name="YAOBI_LR_08" bar="51" pos="0" end_bar="55" end_pos="0" />
    <Camera name="YAOBI_RL_03" bar="55" pos="0" end_bar="59" end_pos="0" />
    <Camera name="TL" bar="59" pos="0" end_bar="61" end_pos="0" />
    <Camera name="YAOBI_UD_LEFT" bar="61" pos="0" end_bar="63" end_pos="0" />
    <Camera name="YAOBI_NF_05" bar="63" pos="0" end_bar="67" end_pos="0" />
    <Camera name="FC" bar="67" pos="0" end_bar="71" end_pos="0" />
  </CameraSeq>
  <DancerSort>
    <Bar>15</Bar>
    <Bar>17</Bar>
    <Bar>19</Bar>
    <Bar>21</Bar>
    <Bar>23</Bar>
    <Bar>25</Bar>
    <Bar>27</Bar>
    <Bar>29</Bar>
    <Bar>31</Bar>
    <Bar>39</Bar>
    <Bar>40</Bar>
    <Bar>41</Bar>
    <Bar>43</Bar>
    <Bar>45</Bar>
    <Bar>47</Bar>
    <Bar>49</Bar>
    <Bar>51</Bar>
    <Bar>53</Bar>
    <Bar>55</Bar>
    <Bar>57</Bar>
    <Bar>59</Bar>
    <Bar>61</Bar>
    <Bar>63</Bar>
    <Bar>65</Bar>
  </DancerSort>
  <StageEffectSeq>
    <effect name="wutai_scene_global_script" bar="-1" length="-1" />
    <effect name="wutai_scene_note_biaozhun_01" bar="9" length="24" />
    <effect name="wutai_scene_note_biaozhun_01" bar="37" length="30" />
    <effect name="wutai_scene_note_biaozhun_01" bar="71" length="-1" />
  </StageEffectSeq>
</Level>