<?xml version="1.0" encoding="utf-8"?>
<Level>
  <LevelInfo>
    <BPM>98</BPM>
    <BeatPerBar>4</BeatPerBar>
    <BeatLen>16</BeatLen>
    <EnterTimeAdjust>12449</EnterTimeAdjust>
    <NotePreShow>2</NotePreShow>
    <LevelTime>156734</LevelTime>
    <BarAmount>64</BarAmount>
    <BeginBarLen>8</BeginBarLen>
    <IsFourTrack>False</IsFourTrack>
    <TrackCount>5</TrackCount>
    <LevelPreTime>4000</LevelPreTime>
  </LevelInfo>
  <MusicInfo>
    <Title>才华有限公司</Title>
    <Artist>金玟岐</Artist>
    <FilePath>audio/bgm/102825</FilePath>
  </MusicInfo>
  <SectionSeq>
    <Section type="previous" endbar="0" mark="" param1="wutai_scene_pre_script_2" />
    <Section type="begin" startbar="1" endbar="8" mark="" param1="wutai_scene_begin_script_2" />
    <Section type="note" startbar="9" endbar="32" mark="" param1="" />
    <Section type="showtime" startbar="33" endbar="36" mark="dance" param1="" />
    <Section type="note" startbar="39" endbar="60" mark="" param1="" />
    <Section type="showtime" startbar="61" endbar="64" mark="pose_yangguang" param1="" />
  </SectionSeq>
  <IndicatorResetPos PosNum="64">
    <Pos Bar="9" BeatPos="0" />
    <Pos Bar="11" BeatPos="0" />
    <Pos Bar="13" BeatPos="0" />
    <Pos Bar="17" BeatPos="0" />
    <Pos Bar="20" BeatPos="48" />
    <Pos Bar="24" BeatPos="32" />
    <Pos Bar="26" BeatPos="32" />
    <Pos Bar="28" BeatPos="32" />
    <Pos Bar="39" BeatPos="0" />
    <Pos Bar="42" BeatPos="32" />
    <Pos Bar="44" BeatPos="32" />
    <Pos Bar="48" BeatPos="32" />
    <Pos Bar="52" BeatPos="32" />
    <Pos Bar="55" BeatPos="0" />
    <Pos Bar="57" BeatPos="32" />
  </IndicatorResetPos>
  <NoteInfo>
    <Normal PosNum="64">
      <Note Bar="9" BeatPos="0" Track="0" Type="0">
        <ScreenPos x="350" y="200">
          <FlyTrack name="波浪形" degree="355.0708" />
        </ScreenPos>
      </Note>
      <Note Bar="9" BeatPos="32" Track="0" Type="0">
        <ScreenPos x="-350" y="-300">
          <FlyTrack name="波浪形" degree="80.88686" />
        </ScreenPos>
      </Note>
      <Note Bar="10" BeatPos="0" Track="0" Type="0">
        <ScreenPos x="550" y="-300">
          <FlyTrack name="波浪形" degree="-6.250214" />
        </ScreenPos>
      </Note>
      <Note Bar="10" BeatPos="32" Track="0" Type="0">
        <ScreenPos x="-400" y="200">
          <FlyTrack name="波浪形" degree="257.666" />
        </ScreenPos>
      </Note>
      <Note Bar="11" BeatPos="0" Track="0" Type="0">
        <ScreenPos x="600" y="200">
          <FlyTrack name="波浪形" degree="354.5761" />
        </ScreenPos>
      </Note>
      <Note Bar="11" BeatPos="32" Track="0" Type="0">
        <ScreenPos x="150" y="-300">
          <FlyTrack name="波浪形" degree="80.65321" />
        </ScreenPos>
      </Note>
      <Note Bar="12" BeatPos="0" Track="0" Type="0">
        <ScreenPos x="-550" y="200">
          <FlyTrack name="波浪形" degree="172.361" />
        </ScreenPos>
      </Note>
      <Note Bar="12" BeatPos="16" Track="0" Type="0">
        <ScreenPos x="-550" y="-300">
          <FlyTrack name="波浪形" degree="83.18485" />
        </ScreenPos>
      </Note>
      <Note Bar="12" BeatPos="24" Track="0" Type="1" EndBar="12" EndPos="40" ID="1">
        <MoveTrack name="长按直线2" degree="-35.81116" />
        <FlyTrack name="波浪形" degree="83.41934" />
        <ScreenPos x="-350" y="-300" />
      </Note>
      <Note Bar="13" BeatPos="0" Track="0" Type="0">
        <ScreenPos x="450" y="200">
          <FlyTrack name="波浪形" degree="-3.340958" />
        </ScreenPos>
      </Note>
      <Note Bar="13" BeatPos="32" Track="0" Type="0">
        <ScreenPos x="-400" y="-300">
          <FlyTrack name="波浪形" degree="174.4637" />
        </ScreenPos>
      </Note>
      <Note Bar="14" BeatPos="0" Track="0" Type="0">
        <ScreenPos x="450" y="-300">
          <FlyTrack name="波浪形" degree="353.9306" />
        </ScreenPos>
      </Note>
      <Note Bar="14" BeatPos="32" Track="0" Type="0">
        <ScreenPos x="-500" y="200">
          <FlyTrack name="波浪形" degree="173.9386" />
        </ScreenPos>
      </Note>
      <Note Bar="15" BeatPos="0" Track="0" Type="0">
        <ScreenPos x="250" y="-300">
          <FlyTrack name="波浪形" degree="79.73925" />
        </ScreenPos>
      </Note>
      <Note Bar="15" BeatPos="8" Track="0" Type="1" EndBar="15" EndPos="24" ID="2">
        <MoveTrack name="长按直线2" degree="0" />
        <FlyTrack name="波浪形" degree="81.77265" />
        <ScreenPos x="450" y="-300" />
      </Note>
      <Note Bar="15" BeatPos="48" Track="0" Type="0">
        <ScreenPos x="-500" y="200">
          <FlyTrack name="波浪形" degree="261.2478" />
        </ScreenPos>
      </Note>
      <Note Bar="15" BeatPos="56" Track="0" Type="1" EndBar="16" EndPos="8" ID="3">
        <MoveTrack name="长按直线2" degree="0" />
        <FlyTrack name="波浪形" degree="258.6178" />
        <ScreenPos x="-300" y="200" />
      </Note>
      <Note Bar="17" BeatPos="0" Track="0" Type="0">
        <ScreenPos x="350" y="-300">
          <FlyTrack name="波浪形" degree="79.00197" />
        </ScreenPos>
      </Note>
      <Note Bar="17" BeatPos="32" Track="0" Type="0">
        <ScreenPos x="-450" y="-300">
          <FlyTrack name="波浪形" degree="170.9962" />
        </ScreenPos>
      </Note>
      <Note Bar="18" BeatPos="0" Track="0" Type="0">
        <ScreenPos x="350" y="200">
          <FlyTrack name="波浪形" degree="-3.063904" />
        </ScreenPos>
      </Note>
      <Note Bar="18" BeatPos="8" Track="0" Type="0">
        <ScreenPos x="350" y="0">
          <FlyTrack name="波浪形" degree="349.7196" />
        </ScreenPos>
      </Note>
      <Note Bar="18" BeatPos="24" Track="0" Type="1" EndBar="18" EndPos="40" ID="4">
        <MoveTrack name="长按直线2" degree="270" />
        <FlyTrack name="波浪形" degree="173.6446" />
        <ScreenPos x="-400" y="-300" />
      </Note>
      <Note Bar="19" BeatPos="0" Track="0" Type="0">
        <ScreenPos x="500" y="-300">
          <FlyTrack name="波浪形" degree="-3.958359" />
        </ScreenPos>
      </Note>
      <Note Bar="19" BeatPos="32" Track="0" Type="0">
        <ScreenPos x="-500" y="200">
          <FlyTrack name="波浪形" degree="-99.05752" />
        </ScreenPos>
      </Note>
      <Note Bar="19" BeatPos="48" Track="0" Type="0">
        <ScreenPos x="200" y="200">
          <FlyTrack name="波浪形" degree="-101.4808" />
        </ScreenPos>
      </Note>
      <Note Bar="19" BeatPos="56" Track="0" Type="0">
        <ScreenPos x="400" y="200">
          <FlyTrack name="波浪形" degree="-104.4264" />
        </ScreenPos>
      </Note>
      <Note Bar="20" BeatPos="8" Track="0" Type="1" EndBar="20" EndPos="24" ID="5">
        <MoveTrack name="长按直线2" degree="-180" />
        <FlyTrack name="波浪形" degree="83.43381" />
        <ScreenPos x="400" y="-300" />
      </Note>
      <Note Bar="20" BeatPos="48" Track="0" Type="0">
        <ScreenPos x="-500" y="-300">
          <FlyTrack name="波浪形" degree="173.2832" />
        </ScreenPos>
      </Note>
      <Note Bar="21" BeatPos="0" Track="0" Type="0">
        <ScreenPos x="-500" y="200">
          <FlyTrack name="波浪形" degree="261.8819" />
        </ScreenPos>
      </Note>
      <Note Bar="21" BeatPos="8" Track="0" Type="1" EndBar="21" EndPos="24" ID="6">
        <MoveTrack name="长按直线2" degree="0" />
        <FlyTrack name="波浪形" degree="260.8645" />
        <ScreenPos x="-300" y="200" />
      </Note>
      <Note Bar="21" BeatPos="24" Track="0" Type="0">
        <ScreenPos x="500" y="200">
          <FlyTrack name="波浪形" degree="-3.572495" />
        </ScreenPos>
      </Note>
      <Note Bar="22" BeatPos="0" Track="0" Type="0">
        <ScreenPos x="-400" y="-300">
          <FlyTrack name="波浪形" degree="84.60593" />
        </ScreenPos>
      </Note>
      <Note Bar="22" BeatPos="16" Track="0" Type="0">
        <ScreenPos x="300" y="-300">
          <FlyTrack name="波浪形" degree="352.5794" />
        </ScreenPos>
      </Note>
      <Note Bar="22" BeatPos="24" Track="0" Type="1" EndBar="22" EndPos="40" ID="7">
        <MoveTrack name="长按直线2" degree="-122.6228" />
        <FlyTrack name="波浪形" degree="352.3451" />
        <ScreenPos x="300" y="-100" />
      </Note>
      <Note Bar="23" BeatPos="0" Track="0" Type="0">
        <ScreenPos x="-500" y="200">
          <FlyTrack name="波浪形" degree="172.7516" />
        </ScreenPos>
      </Note>
      <Note Bar="23" BeatPos="32" Track="0" Type="0">
        <ScreenPos x="400" y="-300">
          <FlyTrack name="波浪形" degree="81.20853" />
        </ScreenPos>
      </Note>
      <Note Bar="23" BeatPos="40" Track="0" Type="0">
        <ScreenPos x="200" y="-300">
          <FlyTrack name="波浪形" degree="80.43971" />
        </ScreenPos>
      </Note>
      <Note Bar="23" BeatPos="56" Track="0" Type="0">
        <ScreenPos x="-500" y="-300">
          <FlyTrack name="波浪形" degree="171.9818" />
        </ScreenPos>
      </Note>
      <Note Bar="24" BeatPos="8" Track="0" Type="0">
        <ScreenPos x="-500" y="200">
          <FlyTrack name="波浪形" degree="261.7423" />
        </ScreenPos>
      </Note>
      <Note Bar="24" BeatPos="32" Track="0" Type="0">
        <ScreenPos x="450" y="200">
          <FlyTrack name="波浪形" degree="353.1855" />
        </ScreenPos>
      </Note>
      <Note Bar="25" BeatPos="0" Track="0" Type="0">
        <ScreenPos x="-350" y="-300">
          <FlyTrack name="波浪形" degree="81.02298" />
        </ScreenPos>
      </Note>
      <Note Bar="25" BeatPos="32" Track="0" Type="0">
        <ScreenPos x="250" y="-300">
          <FlyTrack name="波浪形" degree="82.05197" />
        </ScreenPos>
      </Note>
      <Note Bar="25" BeatPos="40" Track="0" Type="0">
        <ScreenPos x="450" y="-300">
          <FlyTrack name="波浪形" degree="82.10213" />
        </ScreenPos>
      </Note>
      <Note Bar="25" BeatPos="56" Track="0" Type="1" EndBar="26" EndPos="8" ID="8">
        <MoveTrack name="长按直线2" degree="180" />
        <FlyTrack name="波浪形" degree="259.7792" />
        <ScreenPos x="450" y="200" />
      </Note>
      <Note Bar="26" BeatPos="32" Track="0" Type="0">
        <ScreenPos x="-550" y="200">
          <FlyTrack name="波浪形" degree="173.113" />
        </ScreenPos>
      </Note>
      <Note Bar="27" BeatPos="0" Track="0" Type="0">
        <ScreenPos x="-150" y="-300">
          <FlyTrack name="波浪形" degree="80.63596" />
        </ScreenPos>
      </Note>
      <Note Bar="27" BeatPos="32" Track="0" Type="0">
        <ScreenPos x="550" y="-300">
          <FlyTrack name="波浪形" degree="-5.651535" />
        </ScreenPos>
      </Note>
      <Note Bar="27" BeatPos="48" Track="0" Type="0">
        <ScreenPos x="550" y="200">
          <FlyTrack name="波浪形" degree="262.9343" />
        </ScreenPos>
      </Note>
      <Note Bar="27" BeatPos="56" Track="0" Type="1" EndBar="28" EndPos="8" ID="9">
        <MoveTrack name="长按直线2" degree="-209.3194" />
        <FlyTrack name="波浪形" degree="262.9114" />
        <ScreenPos x="350" y="200" />
      </Note>
      <Note Bar="28" BeatPos="32" Track="0" Type="0">
        <ScreenPos x="-400" y="-300">
          <FlyTrack name="波浪形" degree="81.28334" />
        </ScreenPos>
      </Note>
      <Note Bar="29" BeatPos="0" Track="0" Type="0">
        <ScreenPos x="350" y="200">
          <FlyTrack name="波浪形" degree="259.3973" />
        </ScreenPos>
      </Note>
      <Note Bar="29" BeatPos="32" Track="0" Type="0">
        <ScreenPos x="-500" y="200">
          <FlyTrack name="波浪形" degree="258.1846" />
        </ScreenPos>
      </Note>
      <Note Bar="29" BeatPos="40" Track="0" Type="0">
        <ScreenPos x="-300" y="200">
          <FlyTrack name="波浪形" degree="259.87" />
        </ScreenPos>
      </Note>
      <Note Bar="29" BeatPos="56" Track="0" Type="1" EndBar="30" EndPos="16" ID="10">
        <MoveTrack name="长按直线1.5" degree="-180" />
        <FlyTrack name="波浪形" degree="80.63229" />
        <ScreenPos x="400" y="-250" />
      </Note>
      <Note Bar="30" BeatPos="32" Track="0" Type="0">
        <ScreenPos x="-500" y="-250">
          <FlyTrack name="波浪形" degree="173.2099" />
        </ScreenPos>
      </Note>
      <Note Bar="31" BeatPos="0" Track="0" Type="0">
        <ScreenPos x="-200" y="200">
          <FlyTrack name="波浪形" degree="262.2573" />
        </ScreenPos>
      </Note>
      <Note Bar="31" BeatPos="32" Track="0" Type="0">
        <ScreenPos x="400" y="-300">
          <FlyTrack name="波浪形" degree="84.40887" />
        </ScreenPos>
      </Note>
      <Note Bar="31" BeatPos="48" Track="0" Type="0">
        <ScreenPos x="-300" y="-300">
          <FlyTrack name="波浪形" degree="173.9616" />
        </ScreenPos>
      </Note>
      <Note Bar="31" BeatPos="56" Track="0" Type="1" EndBar="32" EndPos="8" ID="11">
        <MoveTrack name="长按直线2" degree="-90" />
        <FlyTrack name="波浪形" degree="171.4686" />
        <ScreenPos x="-300" y="-100" />
      </Note>
      <Note Bar="32" BeatPos="32" Track="0" Type="0">
        <ScreenPos x="400" y="200">
          <FlyTrack name="波浪形" degree="261.8043" />
        </ScreenPos>
      </Note>
      <Note Bar="39" BeatPos="0" Track="4" Type="0">
        <ScreenPos x="500" y="200">
          <FlyTrack name="波浪形" degree="354.8745" />
        </ScreenPos>
      </Note>
      <Note Bar="39" BeatPos="32" Track="4" Type="0">
        <ScreenPos x="-450" y="-300">
          <FlyTrack name="波浪形" degree="82.04002" />
        </ScreenPos>
      </Note>
      <Note Bar="39" BeatPos="40" Track="4" Type="0">
        <ScreenPos x="-250" y="-300">
          <FlyTrack name="波浪形" degree="81.59441" />
        </ScreenPos>
      </Note>
      <Note Bar="39" BeatPos="56" Track="4" Type="1" EndBar="40" EndPos="8" ID="12">
        <MoveTrack name="长按直线2" degree="305.8266" />
        <FlyTrack name="波浪形" degree="82.13208" />
        <ScreenPos x="350" y="-300" />
      </Note>
      <Note Bar="40" BeatPos="32" Track="4" Type="0">
        <ScreenPos x="-450" y="200">
          <FlyTrack name="波浪形" degree="-185.8429" />
        </ScreenPos>
      </Note>
      <Note Bar="41" BeatPos="0" Track="4" Type="0">
        <ScreenPos x="350" y="-300">
          <FlyTrack name="波浪形" degree="84.00003" />
        </ScreenPos>
      </Note>
      <Note Bar="41" BeatPos="32" Track="4" Type="0">
        <ScreenPos x="-250" y="-300">
          <FlyTrack name="波浪形" degree="81.4749" />
        </ScreenPos>
      </Note>
      <Note Bar="41" BeatPos="40" Track="4" Type="0">
        <ScreenPos x="-450" y="-300">
          <FlyTrack name="波浪形" degree="83.39227" />
        </ScreenPos>
      </Note>
      <Note Bar="41" BeatPos="56" Track="4" Type="1" EndBar="42" EndPos="8" ID="13">
        <MoveTrack name="长按直线2" degree="0" />
        <FlyTrack name="波浪形" degree="-95.12926" />
        <ScreenPos x="-450" y="200" />
      </Note>
      <Note Bar="42" BeatPos="32" Track="4" Type="0">
        <ScreenPos x="550" y="200">
          <FlyTrack name="波浪形" degree="354.4796" />
        </ScreenPos>
      </Note>
      <Note Bar="43" BeatPos="0" Track="4" Type="0">
        <ScreenPos x="150" y="-300">
          <FlyTrack name="波浪形" degree="82.06763" />
        </ScreenPos>
      </Note>
      <Note Bar="43" BeatPos="32" Track="4" Type="0">
        <ScreenPos x="-550" y="-300">
          <FlyTrack name="波浪形" degree="174.6697" />
        </ScreenPos>
      </Note>
      <Note Bar="43" BeatPos="48" Track="4" Type="0">
        <ScreenPos x="-550" y="200">
          <FlyTrack name="波浪形" degree="-96.52104" />
        </ScreenPos>
      </Note>
      <Note Bar="43" BeatPos="56" Track="4" Type="1" EndBar="44" EndPos="8" ID="14">
        <MoveTrack name="长按直线2" degree="29.3194" />
        <FlyTrack name="波浪形" degree="-97.67678" />
        <ScreenPos x="-350" y="200" />
      </Note>
      <Note Bar="44" BeatPos="32" Track="4" Type="0">
        <ScreenPos x="400" y="-300">
          <FlyTrack name="波浪形" degree="80.96321" />
        </ScreenPos>
      </Note>
      <Note Bar="45" BeatPos="0" Track="4" Type="0">
        <ScreenPos x="-350" y="200">
          <FlyTrack name="波浪形" degree="-99.04823" />
        </ScreenPos>
      </Note>
      <Note Bar="45" BeatPos="32" Track="4" Type="0">
        <ScreenPos x="500" y="200">
          <FlyTrack name="波浪形" degree="-98.58017" />
        </ScreenPos>
      </Note>
      <Note Bar="45" BeatPos="40" Track="4" Type="0">
        <ScreenPos x="300" y="200">
          <FlyTrack name="波浪形" degree="-97.6907" />
        </ScreenPos>
      </Note>
      <Note Bar="45" BeatPos="56" Track="4" Type="1" EndBar="46" EndPos="16" ID="15">
        <MoveTrack name="长按直线1.5" degree="360" />
        <FlyTrack name="波浪形" degree="78.66658" />
        <ScreenPos x="-400" y="-250" />
      </Note>
      <Note Bar="46" BeatPos="32" Track="4" Type="0">
        <ScreenPos x="500" y="-250">
          <FlyTrack name="波浪形" degree="-5.887772" />
        </ScreenPos>
      </Note>
      <Note Bar="47" BeatPos="0" Track="4" Type="0">
        <ScreenPos x="200" y="200">
          <FlyTrack name="波浪形" degree="-97.95294" />
        </ScreenPos>
      </Note>
      <Note Bar="47" BeatPos="32" Track="4" Type="0">
        <ScreenPos x="-400" y="-300">
          <FlyTrack name="波浪形" degree="83.03647" />
        </ScreenPos>
      </Note>
      <Note Bar="47" BeatPos="48" Track="4" Type="0">
        <ScreenPos x="300" y="-300">
          <FlyTrack name="波浪形" degree="-3.852798" />
        </ScreenPos>
      </Note>
      <Note Bar="47" BeatPos="56" Track="4" Type="1" EndBar="48" EndPos="16" ID="16">
        <MoveTrack name="长按直线1.5" degree="270" />
        <FlyTrack name="波浪形" degree="-6.08905" />
        <ScreenPos x="300" y="-100" />
      </Note>
      <Note Bar="48" BeatPos="32" Track="4" Type="0">
        <ScreenPos x="-450" y="200">
          <FlyTrack name="波浪形" degree="-185.8896" />
        </ScreenPos>
      </Note>
      <Note Bar="49" BeatPos="0" Track="4" Type="0">
        <ScreenPos x="350" y="-300">
          <FlyTrack name="波浪形" degree="82.50527" />
        </ScreenPos>
      </Note>
      <Note Bar="49" BeatPos="32" Track="4" Type="0">
        <ScreenPos x="-250" y="-300">
          <FlyTrack name="波浪形" degree="82.01542" />
        </ScreenPos>
      </Note>
      <Note Bar="49" BeatPos="40" Track="4" Type="0">
        <ScreenPos x="-450" y="-300">
          <FlyTrack name="波浪形" degree="81.57669" />
        </ScreenPos>
      </Note>
      <Note Bar="49" BeatPos="56" Track="4" Type="1" EndBar="50" EndPos="8" ID="17">
        <MoveTrack name="长按直线2" degree="0" />
        <FlyTrack name="波浪形" degree="-94.39873" />
        <ScreenPos x="-450" y="200" />
      </Note>
      <Note Bar="50" BeatPos="32" Track="4" Type="0">
        <ScreenPos x="550" y="200">
          <FlyTrack name="波浪形" degree="354.3435" />
        </ScreenPos>
      </Note>
      <Note Bar="51" BeatPos="0" Track="4" Type="0">
        <ScreenPos x="150" y="-300">
          <FlyTrack name="波浪形" degree="81.47504" />
        </ScreenPos>
      </Note>
      <Note Bar="51" BeatPos="32" Track="3" Type="0">
        <ScreenPos x="-450" y="200">
          <FlyTrack name="波浪形" degree="175.8418" />
        </ScreenPos>
      </Note>
      <Note Bar="51" BeatPos="48" Track="3" Type="0">
        <ScreenPos x="400" y="200">
          <FlyTrack name="波浪形" degree="-4.379837" />
        </ScreenPos>
      </Note>
      <Note Bar="51" BeatPos="56" Track="3" Type="0">
        <ScreenPos x="400" y="0">
          <FlyTrack name="波浪形" degree="-5.925171" />
        </ScreenPos>
      </Note>
      <Note Bar="52" BeatPos="8" Track="3" Type="1" EndBar="52" EndPos="24" ID="18">
        <MoveTrack name="长按直线2" degree="-90" />
        <FlyTrack name="波浪形" degree="173.3937" />
        <ScreenPos x="-400" y="-300" />
      </Note>
      <Note Bar="52" BeatPos="32" Track="3" Type="0">
        <ScreenPos x="400" y="-300">
          <FlyTrack name="波浪形" degree="354.9244" />
        </ScreenPos>
      </Note>
      <Note Bar="53" BeatPos="0" Track="3" Type="0">
        <ScreenPos x="-400" y="200">
          <FlyTrack name="波浪形" degree="260.7406" />
        </ScreenPos>
      </Note>
      <Note Bar="53" BeatPos="32" Track="3" Type="0">
        <ScreenPos x="500" y="200">
          <FlyTrack name="波浪形" degree="354.2297" />
        </ScreenPos>
      </Note>
      <Note Bar="53" BeatPos="48" Track="3" Type="0">
        <ScreenPos x="500" y="-250">
          <FlyTrack name="波浪形" degree="-277.041" />
        </ScreenPos>
      </Note>
      <Note Bar="53" BeatPos="56" Track="3" Type="1" EndBar="54" EndPos="8" ID="19">
        <MoveTrack name="长按直线2" degree="210.6211" />
        <FlyTrack name="波浪形" degree="80.23386" />
        <ScreenPos x="300" y="-250" />
      </Note>
      <Note Bar="54" BeatPos="8" Track="3" Type="0">
        <ScreenPos x="-400" y="-250">
          <FlyTrack name="波浪形" degree="154.309" />
        </ScreenPos>
      </Note>
      <Note Bar="54" BeatPos="16" Track="3" Type="0">
        <ScreenPos x="-550" y="-50">
          <FlyTrack name="波浪形" degree="179.1007" />
        </ScreenPos>
      </Note>
      <Note Bar="54" BeatPos="24" Track="3" Type="0">
        <ScreenPos x="-400" y="150">
          <FlyTrack name="波浪形" degree="204.8562" />
        </ScreenPos>
      </Note>
      <Note Bar="55" BeatPos="0" Track="3" Type="0">
        <ScreenPos x="450" y="150">
          <FlyTrack name="波浪形" degree="-4.899551" />
        </ScreenPos>
      </Note>
      <Note Bar="55" BeatPos="32" Track="3" Type="0">
        <ScreenPos x="-250" y="-300">
          <FlyTrack name="波浪形" degree="82.357" />
        </ScreenPos>
      </Note>
      <Note Bar="55" BeatPos="40" Track="3" Type="0">
        <ScreenPos x="-450" y="-300">
          <FlyTrack name="波浪形" degree="81.27846" />
        </ScreenPos>
      </Note>
      <Note Bar="55" BeatPos="56" Track="3" Type="1" EndBar="56" EndPos="8" ID="20">
        <MoveTrack name="长按直线2" degree="0" />
        <FlyTrack name="波浪形" degree="265.3903" />
        <ScreenPos x="-450" y="200" />
      </Note>
      <Note Bar="56" BeatPos="16" Track="3" Type="0">
        <ScreenPos x="400" y="200">
          <FlyTrack name="波浪形" degree="-3.414261" />
        </ScreenPos>
      </Note>
      <Note Bar="56" BeatPos="32" Track="3" Type="0">
        <ScreenPos x="400" y="-300">
          <FlyTrack name="波浪形" degree="81.39196" />
        </ScreenPos>
      </Note>
      <Note Bar="56" BeatPos="40" Track="3" Type="0">
        <ScreenPos x="200" y="-300">
          <FlyTrack name="波浪形" degree="80.46448" />
        </ScreenPos>
      </Note>
      <Note Bar="56" BeatPos="56" Track="3" Type="1" EndBar="57" EndPos="8" ID="21">
        <MoveTrack name="长按直线2" degree="-89.43225" />
        <FlyTrack name="波浪形" degree="173.6671" />
        <ScreenPos x="-350" y="-300" />
      </Note>
      <Note Bar="57" BeatPos="32" Track="3" Type="0">
        <ScreenPos x="350" y="150">
          <FlyTrack name="波浪形" degree="0" />
        </ScreenPos>
      </Note>
      <Note Bar="58" BeatPos="16" Track="3" Type="0">
        <ScreenPos x="-300" y="-250">
          <FlyTrack name="波浪形" degree="80.0203" />
        </ScreenPos>
      </Note>
      <Note Bar="58" BeatPos="32" Track="3" Type="0">
        <ScreenPos x="300" y="-250">
          <FlyTrack name="波浪形" degree="356.1439" />
        </ScreenPos>
      </Note>
      <Note Bar="59" BeatPos="16" Track="3" Type="0">
        <ScreenPos x="-400" y="200">
          <FlyTrack name="波浪形" degree="173.3247" />
        </ScreenPos>
      </Note>
      <Note Bar="59" BeatPos="32" Track="3" Type="0">
        <ScreenPos x="150" y="-300">
          <FlyTrack name="波浪形" degree="-276.8495" />
        </ScreenPos>
      </Note>
      <Note Bar="59" BeatPos="40" Track="3" Type="0">
        <ScreenPos x="350" y="-300">
          <FlyTrack name="波浪形" degree="82.35468" />
        </ScreenPos>
      </Note>
      <Note Bar="59" BeatPos="56" Track="3" Type="1" EndBar="60" EndPos="24" ID="22">
        <MoveTrack name="长按波浪2拍" degree="185.5477" />
        <FlyTrack name="波浪形" degree="258.9126" />
        <ScreenPos x="350" y="200" />
      </Note>
    </Normal>
  </NoteInfo>
  <ActionSeq type="1">
    <ActionList start_bar="9" dance_len="1" seq_len="4" level="2" type="" />
    <ActionList start_bar="13" dance_len="2" seq_len="4" level="2" type="" />
    <ActionList start_bar="17" dance_len="2" seq_len="4" level="2" type="" />
    <ActionList start_bar="21" dance_len="2" seq_len="4" level="2" type="" />
    <ActionList start_bar="25" dance_len="2" seq_len="8" level="2" type="" />
    <ActionList start_bar="33" dance_len="4" seq_len="4" level="2" type="" />
    <ActionList start_bar="37" dance_len="1" seq_len="4" level="2" type="" />
    <ActionList start_bar="41" dance_len="2" seq_len="4" level="2" type="" />
    <ActionList start_bar="45" dance_len="2" seq_len="4" level="2" type="" />
    <ActionList start_bar="49" dance_len="2" seq_len="8" level="2" type="" />
    <ActionList start_bar="57" dance_len="2" seq_len="4" level="2" type="" />
    <ActionList start_bar="61" dance_len="4" seq_len="4" level="2" type="" />
  </ActionSeq>
  <CameraSeq>
    <Camera name="NL" bar="9" pos="0" end_bar="11" end_pos="0" />
    <Camera name="SR" bar="11" pos="0" end_bar="13" end_pos="0" />
    <Camera name="YAOBI_RL_01" bar="13" pos="0" end_bar="15" end_pos="0" />
    <Camera name="YAOBI_UD_CENTER" bar="15" pos="0" end_bar="17" end_pos="0" />
    <Camera name="NR" bar="17" pos="0" end_bar="19" end_pos="0" />
    <Camera name="SL" bar="19" pos="0" end_bar="21" end_pos="0" />
    <Camera name="T_LR_01" bar="21" pos="0" end_bar="23" end_pos="0" />
    <Camera name="YAOBI_FN_01" bar="23" pos="0" end_bar="25" end_pos="0" />
    <Camera name="YAOBI_RL_05" bar="25" pos="0" end_bar="27" end_pos="0" />
    <Camera name="YAOBI_NF_01" bar="27" pos="0" end_bar="29" end_pos="0" />
    <Camera name="NR" bar="29" pos="0" end_bar="30" end_pos="0" />
    <Camera name="SL" bar="30" pos="0" end_bar="31" end_pos="0" />
    <Camera name="YAOBI_NF_07" bar="31" pos="0" end_bar="33" end_pos="0" />
    <Camera name="NC" bar="33" pos="0" end_bar="37" end_pos="0" />
    <Camera name="YAOBI_RL_01" bar="37" pos="0" end_bar="39" end_pos="0" />
    <Camera name="YAOBI_FN_01" bar="39" pos="0" end_bar="41" end_pos="0" />
    <Camera name="SR" bar="41" pos="0" end_bar="43" end_pos="0" />
    <Camera name="NL" bar="43" pos="0" end_bar="45" end_pos="0" />
    <Camera name="YAOBI_LR_02" bar="45" pos="0" end_bar="47" end_pos="0" />
    <Camera name="YAOBI_NF_01" bar="47" pos="0" end_bar="49" end_pos="0" />
    <Camera name="NR" bar="49" pos="0" end_bar="51" end_pos="0" />
    <Camera name="YAOBI_UD_LEFT" bar="51" pos="0" end_bar="53" end_pos="0" />
    <Camera name="NL" bar="53" pos="0" end_bar="55" end_pos="0" />
    <Camera name="YAOBI_UD_RIGHT" bar="55" pos="0" end_bar="57" end_pos="0" />
    <Camera name="YAOBI_BF_01" bar="57" pos="0" end_bar="61" end_pos="0" />
    <Camera name="NC" bar="61" pos="0" end_bar="65" end_pos="0" />
  </CameraSeq>
  <DancerSort>
    <Bar>15</Bar>
    <Bar>17</Bar>
    <Bar>19</Bar>
    <Bar>21</Bar>
    <Bar>23</Bar>
    <Bar>25</Bar>
    <Bar>27</Bar>
    <Bar>29</Bar>
    <Bar>31</Bar>
    <Bar>39</Bar>
    <Bar>40</Bar>
    <Bar>41</Bar>
    <Bar>43</Bar>
    <Bar>45</Bar>
    <Bar>47</Bar>
    <Bar>49</Bar>
    <Bar>51</Bar>
    <Bar>53</Bar>
    <Bar>55</Bar>
    <Bar>57</Bar>
    <Bar>59</Bar>
  </DancerSort>
  <StageEffectSeq>
    <effect name="wutai_scene_global_script" bar="-1" length="-1" />
    <effect name="wutai_scene_note_biaozhun_01" bar="9" length="24" />
    <effect name="wutai_scene_note_biaozhun_01" bar="37" length="24" />
    <effect name="wutai_scene_note_biaozhun_01" bar="65" length="-1" />
  </StageEffectSeq>
</Level>